Workbook

Sheet FrontP
A9: 03 | B9: 44316 | C9: Issued for Review | E9: ALL | F9: OKS/RSS | G9: OKS
A10: 02 | B10: 44279 | C10: Issued for Review | E10: ALL | F10: OKS/RSS | G10: OKS
A11: 01 | B11: 44235 | C11: Issued for Review | E11: ALL | F11: OKS/RSS | G11: OKS
A12: Rev | B12: Issued date | C12: Description | E12: Made by | F12: Chk'd by | G12: Disc. appr. | H12: Proj. appr. | I12: Client appr.
E13: Aibel AS
G14: Client Ref:
G15: 4503943297
A16: Project no: | D16: Project Title:
A17: 007990 | D17: Askja UPP and Krafla Field Engineering C-study
A18: Doc.Type: | D18: Area: | E18: System:
A19: LA | D19: 00 | E19: 00
A21: Document Title:
A22: Master Equipment List (MEL) - Askja Unmanned Process Platform (UPP)
A23: Document no.: | F23: Rev. | H23: Page:
A24: C232-AI-R-LA-00001 | F24: 02 | H24: 1 of 7

Sheet Info
F64: TR1244 Appendix 3 - Master Equipment List (MEL)
B66: Document owner information | G66: Project information
B67: Document ref.: | C67: TR1244 | G67: Project:
B68: Document rev. date: | C68: 44167 | G68: Equinor discipline responsible:
B69: Document approved by: | C69: TPD PRD EP EST | G69: Date:
G70: Rev:
G72: Signature:

Sheet Definitions
B3: MEL Column | C3: Description | D3: Relevant for class
B4: Tag Status | C4: Used for tracking changes from previous MEL version. NEW - Newly added or retagged items. Whole line shall be highlighted DIFF - Item will have a changed entry in at least one of its fields. Affected cells shall be highlighted. Comments shall be used to input the former cell content. EQUAL- No change from last version. | D4: B | E4: C | F4: D
B5: Building block | C5: To be entered if modification scope is divided into different blocks/packages. Project specific codes. | E5: C | F5: D
B6: Discipline | C6: Discipline code, ref. project specific TR0052 ENS (Engineering Numbering System). This is the 'OWNER' discipline of the equipment, as it would be procured . Example: R - Mechanical / E - Electrical / J - Automation / S - Safety | D6: B | E6: C | F6: D
B7: Cost Code COR | C7: Codes for Equipment and Bulk, ref. Standard Cost Coding System – (SCCS), as described in ISO 19008. Four letter codes to be entered for equipment, 3 letter codes for Bulk. Valid codes are given in TR1244 Appendix 4. Code of Resources (COR). | D7: B | E7: C | F7: D
B8: Tag Number | C8: Tag number for the reported item, which identifies a piece of equipment. Tag number to be in accordance with project specific ENS (Engineering Numbering System) ref. TR0052. | D8: B | E8: C | F8: D
B9: Top Tag | C9: Denotes if the tag number is the skid reference. If 'NO' then that item will be mounted on the associated skid reference. If 'YES' then this entry shall summarize the entire skid footprint and weight. | D9: B | E9: C | F9: D
B10: Skid Ref. | C10: Skid reference/ mounted on (if equipment weight is included in parent skid weights). This will define where the overall dimensions and weight are captured. | D10: B | E10: C | F10: D
B11: PO Package Number | C11: Project specific procurement order (PO) number. Only to be filled in when info is available | F11: D
B12: System Number | C12: System number for reported item. System number to be in accordance with project specific ENS (Engineering Numbering System), ref. TR0052. | D12: B | E12: C | F12: D
B13: Equinor Equipment Category (1 - 4) | C13: Equinor equipment categories in accordance with Equinor Standard Equipment List: 1. Industry standard, produced for offshore industry 2. Industry standard with Equinor Specific additional tech. requirements 3. Customized equipment to Equinor technical requirements 4. Multidiscipline package according to Equinor Equipment package list | D13: B | E13: C | F13: D
B14: Equipment Type Description | C14: Description of equipment component and service, item specific. | D14: B | E14: C | F14: D
B15: Area | C15: Area location codes on the platform for reported item, ref. project specific TR0052 ENS (Engineering Numbering System). Platform specific codes. | E15: C | F15: D
B16: Sub Area | C16: Sub area location on the platform for the reported item, to be entered when relevant. Platform specific codes. | E16: C | F16: D
B17: Function Area | C17: For new build projects, areas like separation area, compression area, etc are valid. Used for selecting bulk and structural density factors. For modification projects, this code is not applicable. | F17: D
B18: L / TT (mm) | C18: Lenght (L) of reported equipment / Tangent-to-tangent (TT) distance for horizontal vessels. The TT distance is referring to the straight, cylindrical length of a vessel, excluding the header. | D18: B | E18: C | F18: D
B19: W / ID (mm) | C19: Width (W) of reported equipment / Inner diameter (ID) for vessels. | D19: B | E19: C | F19: D
B20: H / TT (mm) | C20: Height (H) of reported equipment / Tangent-to-tangent (TT) distance for vertical vessels. The TT distance is referring to the straight, cylindrical hight of a vessel, excluding the header. | D20: B | E20: C | F20: D
B21: Footprint (m²) | C21: Equipment footprint area. Footprint = L x W for all equipment. | D21: B | E21: C | F21: D
B22: Modification Phase Code | C22: This code identifies at which stage (weight phase) in the project an item is installed, moved, changed or removed e.g. when a material handling activity takes place. To be used for projects where shutdown(s) is required. | E22: C | F22: D
B23: Modification Construction Code | C23: M - Bulk materials/items/assemblies installed in a module onshore before transport offshore. If there is more than one module, codes M1, M2 etc. should be entered. P - Prefabricated bulk materials/items/assemblies for offshore integration work (i.e. pipe spools, steelwork). I - Bulk materials/items purchased for offshore integration work (items which require NO prefab. work, installation work only, e.g. pumps, valves, cables, instruments etc.). Existing bulk materials/items which are to be moved or removed | D23: B | E23: C | F23: D
B24: Modification Handling Code | C24: New (greenfield) projects: PERM - Permanently installed equipment. TEMP - Temporarily installed equipment. FUT - Equipment installed in the future. Modification (brownfield) projects: NP - New permanently installed material/equipment. CP - Change of Permanently Installed / Revamp For equipment and tagged bulk. A change in design / weight of existing permanently installed item / equipment, i.e. revamp of internals in heat exchanger. Weight of new item installed is to be reported as CP. Weight of the existing part removed is to be reported as RP. MP - Moved Permanently. Material/equipment moved permanently to a new location (or back to its original location) and (re)installed (no changes to the moved object). MP does also include the dismantling ahead of the relocation and temporary moves (if relevant). NT - New temporarily installed material/equipment. Installation of temporary material/equipment. If weights are reported as NT, corresponding weights must be reported under RT. (When weights are reported as NT, corresponding weights are automatically reported as demolition in the summary sheets in TR1244). RT - Removal of Temporary items. Removal of temporarily installed equipment or bulk. Report weight of material/equipment to be dismantled. Ref NT. (When weights are reported as NT, corresponding weights are automatically reported as demolition in the summary sheets in TR1244). RP - Removal of Permanent items. Removal of permanently installed equipment or bulk material. Report weight of material/equipment to be dismantled. | D24: B | E24: C | F24: D
B25: Allowance (%) | C25: A weight allowance shall be added to the net reported weights to account for incompleteness in the definition of equipment, components and materials, ref. TR1244, section for Weight allowance. Weight allowance applied to Net Dry Weight only. | D25: B | E25: C | F25: D
B26: Net Dry Weight (kg) | C26: Equipment dry weight (excluding any allowances) obtained either by estimates from early design documents or present sketches, calculated WTO from drawings or 3D model, or as given in vendor data-sheets, ref. ISO 19901-5. | D26: B | E26: C | F26: D
B27: Gross Dry Weight (kg) | C27: Equipment gross weight, equal to reported weight: Net Dry Weight x (1 + (Weight Allowance/100)), ref. ISO 19901-5. | D27: B | E27: C | F27: D
B28: Content Weight (kg) | C28: Weight of content (fluids) in equipment/bulk during normal operating conditions, ref. ISO 19901-5. | D28: B | E28: C | F28: D
B29: Dry CoG East (mm) | C29: Global Center of Gravity (CoG) for the reported (dry) item in East direction. | E29: C | F29: D
B30: Dry CoG North (mm) | C30: Global Center of Gravity (CoG) for the reported (dry) item in North direction. | E30: C | F30: D
B31: Dry CoG Elevation (mm) | C31: Global Center of Gravity (CoG) for the reported (dry) item in Elevation direction. | E31: C | F31: D
B32: Price Source | C32: Source of the cost entered. Example: In house information/factorized, supplier budget price, etc. Hidden in native document | E32: (C) | F32: (D)
B33: Cost [Proj. currency] | C33: Procurement cost of the equipment in project currency. Procurement cost for offshore projects should be related to toptags alternatively PO numbers and extent is to be defined by project | E33: (C) | F33: (D)
B34: Cost Date | C34: Date for when the price information is obtained. | E34: (C) | F34: (D)
B35: Exch. rate | C35: Exchange rate from project currency to NOK (Norwegian Kroner). | E35: (C) | F35: (D)
B36: NOK | C36: Cost of reported item in NOK (Norwegian Kroner). | E36: (C) | F36: (D)
B37: Pressure 1 (Barg) | C37: Preliminary design pressure for the reported equipment. Generally, Pressure 1 denotes the minimum design pressure and Pressure 2 denotes the maximum design pressure. For mutli-fluid vessels (e.g. heat exchangers), Pressure 1 denotes the inlet pressure of the process medium and Pressure 2 denotes the outlet pressure of the process medium. | D37: Depending on equipment type
B38: Pressure 2 (Barg)
B39: Temp 1 (°C) | C39: Temperature information for reported equipment in degrees Celsius. Temp 2 to be used if more than one temperature needs to be specified. For mutli-fluid vessels (e.g. heat exchangers), Temp 1 denotes the inlet temperature of the process medium and Temp 2 denotes the outlet temperature of the process medium. Temperatures for coolant may be given in Remarks column | D39: Depending on equipment type
B40: Temp 2 (°C)
B41: Flow rate 1 (m³/hr) | C41: Design volumetric flow rate. Generally, Flow rate 1 denotes the minimum flow rate and Flow rate 2 denotes the maximum flow rate. For mutli-fluid vessels (e.g. heat exchangers), Flow rate 1 denotes the flow rate of the process medium and Flowrate 2 denotes the flow rate of the cooling medium. | D41: Depending on equipment type
B42: Flow rate 2 (m³/hr)
B43: Capacity (m³) | C43: Total (gross) capacity information for the reported equipment (e.g. storage tanks). | D43: Depending on equipment type
B44: Heat transfer medium (type) | C44: Type of heat transfer medium used, e.g. glycol, water, TEG/water, seawater, hot oil, steam. | D44: Depending on equipment type
B45: Speed (rpm) | C45: For rotating equipment. Denotes the rotational speed in rounds per minute. | D45: Depending on equipment type
B46: Heat Exchanged per Unit (kW) | C46: For (process) heat exchangers. Denotes the maximum heat exchange case for the item (this is not necessarily the sizing case for the item). | D46: Depending on equipment type
B47: Shaft Power (kW) | C47: For rotating machinery. Denotes the shaft power for the rated duty case for the item (note - this is normally the sizing case for the item). | D47: Depending on equipment type
B48: Rated Power (kW) | C48: For Electrical Items. Denotes the rated power of the equipment. | D48: Depending on equipment type
B49: Heat Transfer Surface Area [m²] | C49: Surface area available for heat transfer of the reported equipment. | D49: Depending on equipment type
B50: Material 1 | C50: Material selection for the reported equipment. Material 2 to be used if more than one material is present for the equipment. For shell-and-tube heat exchangers Material 1 denotes the shell-side material and Material denotes the tube-side material. | D50: Depending on equipment type
B51: Material 2
B52: Reference /Source | C52: Defines the reference source of the equipment information (e.g. calculations and key dimensioning criteria). | D52: B | E52: C | F52: D
B53: Reference doc., dwg., PFD, P&ID etc. | C53: Reference to ensure traceability of the item, such as drawing, PFD, P&ID, document, datasheet etc. | D53: B | E53: C | F53: D
B54: Risk: Weight accuracy | C54: Result of risk assessment for weight accuracy and robustness. • Red: high risk • Yellow: moderate risk • Green: low risk | D54: B | E54: C | F54: D
B55: Risk: Footprint accuracy | C55: Result of risk assessment for footprint accuracy and robustness. • Red: high risk • Yellow: moderate risk • Green: low risk | D55: B | E55: C | F55: D
B56: Risk: Design basis | C56: Result of risk assessment for possible changes caused by design basis development & concept selection uncertainties. • Red: high risk • Yellow: moderate risk • Green: low risk | D56: B | E56: C | F56: D
B57: Risk comments | C57: Comments to the risk levels: • Changes from previous MEL version • Mitigation and/or monitoring actions • Expalination for choice of risk level related to accuracy (risk & weight) and design basis | D57: B | E57: C | F57: D
B58: Remarks | C58: To be used for 'special information' only, shall not be used to convey information / data contained in any of the other columns. • Noise enclosures (need for noise enclosure, additional footprint, HVAC supply, etc.) • For rotating equipment information • Type of driver (e.g. motor, gas turbine, diesel) • Need of gearbox (yes, no) • If lube oil system and seal gas system is included in skid • Special layout considerations • Special area classification requirements • Special elevation requirements • Requirements for location in dedicated rooms • Special requirements regarding access ways, withdrawal, maintenance, escape routes, instrumentation access, material handling, etc. • Equipment lifetime and requirements for replacement during lifetime • Requirements regarding equipment location and access to main transport routes, laydown areas, etc. • Significant deviations detected from comparison with as-built data (Risk assessment result) • Special considerations pending different vendor input • Project specific information • Any other relevant information specifying the equipment | D58: B | E58: C | F58: D
C59: Cells marked in yellow represent a change from previous version. If a red comment marker (in the corner) is present as shown, this will give the former cell entry. | D59: B | E59: C | F59: D

Sheet MEL
A2: MASTER EQUIPMENT LIST Multi discipline input | L2: Rev: | M2: 03 | U2: Total Net Dry Weight | V2: =SUBTOTAL(109,W7:W352) -> 1442398.7 | W2: kg
J3: Do not delete or change row | U3: Total Net Gross Weight | V3: =SUBTOTAL(109,X6:X351) -> 1657230 | W3: kg | X3: Resulting allow: | Y3: =(V3-V2)/V2 -> 0.14894031
A4: Project: | C4: Askja UPP C study | H4: Platform: | I4: Askja UPP | J4: 1-7 or modify columns A to BC. | L4: Date: | M4: 44316 | U4: Total Content Weight | V4: =SUBTOTAL(109,Y7:Y352) -> 278133.61 | W4: kg | AC4: Cost data per toptag/PO only, project to decide extent
A5: BCD | B5: CD | C5: BCD | D5: BCD | E5: BCD | F5: BCD | G5: BCD | H5: (D) | I5: BCD | J5: BCD | K5: BCD | L5: CD | M5: CD | N5: D | O5: BCD | P5: BCD | Q5: BCD | R5: BCD | S5: CD | T5: BCD | U5: BCD | V5: BCD | W5: BCD | X5: BCD | Y5: BCD | Z5: CD | AA5: CD | AB5: CD | AC5: (CD) | AD5: (CD) | AE5: (CD) | AF5: (CD) | AG5: (CD) | AW5: BCD | AX5: BCD | AY5: BCD | AZ5: BCD | BB5: BCD | BC5: BCD
A6: Tag Status | B6: Building block | C6: Discipline | D6: Cost Code COR | E6: Tag Number | F6: Top Tag | G6: Skid Ref. | H6: PO Package Number | I6: System Number | J6: Equinor Equipment Category (1 - 4) | K6: Equipment Type Description | L6: Area | M6: Sub Area | N6: Function Area | O6: L / TT (mm) | P6: W / ID (mm) | Q6: H / TT (mm) | R6: Footprint (m²) | S6: Modification Phase Code | T6: Modification Construction Code | U6: Modification Handling Code | V6: Allowance (%) | W6: Net Dry Weight (kg) | X6: Gross Dry Weight (kg) | Y6: Content Weight (kg) | Z6: Dry CoG East (mm) | AA6: Dry CoG North (mm) | AB6: Dry CoG Elevation (mm) | AC6: Price Source | AD6: Cost [Proj. currency] | AE6: Cost Date | AF6: Exch. rate | AG6: NOK | AH6: Pressure 1 (Barg) | AI6: Pressure 2 (Barg) | AJ6: Temp 1 (°C) | AK6: Temp 2 (°C) | AL6: Flow rate 1 (m³/hr) | AM6: Flow rate 2 (m³/hr) | AN6: Capacity (m³) | AO6: Heat transfer medium (type) | AP6: Speed (RPM) | AQ6: Heat Exchanged per Unit (kW) | AR6: Shaft Power (kW) | AS6: Rated Power (kW) | AT6: Heat Transfer Surface Area [m²] | AU6: Material 1 | AV6: Material 2 | AW6: Reference /Source | AX6: Reference doc., dwg., P&ID etc. | AY6: Risk: Weight accuracy | AZ6: Risk: Footprint accuracy | BA6: Risk: Design basis | BB6: Risk comments | BC6: Remarks | BD6: CLASS_OF_ACTIVITY | BE6: CLASS_OF_FUNCTIONAL_OBJECT | BF6: CLASS_OF_INANIMATE_PHYSICAL_OBJECT
A7: =0 -> 0 | B7: =0 -> 0 | C7: =0 -> 0 | D7: =0 -> 0 | E7: =0 -> 0 | G7: =0 -> 0 | I7: =0 -> 0 | K7: =0 -> 0 | L7: =0 -> 0 | M7: =0 -> 0 | N7: =0 -> 0 | O7: =0 -> 0 | P7: =0 -> 0 | Q7: =0 -> 0 | R7: =0 -> 0 | ... W7: =0 -> 0 | X7: =W7*(1+V7) -> 0 | Y7: =0 -> 0 | Z7: =0 -> 0 | AA7: =0 -> 0 | AB7: =0 -> 0 | AC7: =0 -> 0 | AD7: =0 -> 0 | AE7: =0 -> 0 | AF7: =0 -> 0 | ... AN7: =0 -> 0 | AT7: =0 -> 0 | AU7: =0 -> 0 | AV7: =0 -> 0 | AW7: =0 -> 0 | AX7: =0 -> 0 | BC7: =0 -> 0
A8: DIFF | C8: E | E8: A-18BY001 | H8: - | I8: 18 | K8: Optical Junction Box Central | L8: Cellar deck | M8: AP200 | N8: AP200 | O8: 1000 | P8: 800 | Q8: 400 | R8: =(O8*P8)/1000000 -> 0.8 | U8: PERM | V8: 0.15 | W8: 300 | X8: =W8*(1+V8) -> 345 | BC8: Interface Patch boxes for subsea cables
A9: DIFF | C9: E | E9: A-18BY002 | H9: - | I9: 18 | K9: Optical Junction Box for UID | L9: Cellar deck | M9: AP200 | N9: AP200 | O9: 1000 | P9: 800 | Q9: 400 | R9: =(O9*P9)/1000000 -> 0.8 | U9: PERM | V9: 0.15 | W9: 300 | X9: =W9*(1+V9) -> 345 | BC9: Interface Patch boxes for subsea cables. To be used for UID
C10: J | D10: ERCT | E10: A-18CT001 | H10: EI001 | I10: 18 | K10: Hydraulic Power Unit (LP and HP) | L10: Cellar deck | M10: AP200 | N10: AP200 | O10: 5300 | P10: 2400 | Q10: 3000 | R10: =(O10*P10)/1000000 -> 12.72 | U10: PERM | V10: 0.15 | W10: 10000 | X10: =W10*(1+V10) -> 11500 | Y10: 4000 | Z10: 320199 | AA10: 396399 | AB10: 514025 | BC10: Based on Cre8 GA ,Size and number of connections to be updated due to new field configurairion
C11: J | D11: EJJF | E11: A-18JC001 | H11: CPI | I11: 18 | K11: DAS/DTS system cabinet | L11: Cellar deck | M11: AQ200 | N11: AQ200 | O11: 1000 | P11: 800 | Q11: 2000 | R11: =(O11*P11)/1000000 -> 0.8 | U11: PERM | V11: 0.15 | W11: 300 | X11: =W11*(1+V11) -> 345 | Z11: 326290 | AA11: 383938 | AB11: 502360
C12: J | E12: A-18JF001 | H12: CPI | I12: 18 | K12: DAS/DTS Fibre splice cabinet | L12: Cellar deck | M12: AP200 | N12: AP200 | O12: 1000 | P12: 800 | Q12: 2000 | R12: =(O12*P12)/1000000 -> 0.8 | U12: PERM | V12: 0.15 | W12: 300 | X12: =W12*(1+V12) -> 345
A13: NEW | C13: J | D13: EJJF | E13: A-18JF002 | H13: CPI | I13: 18 | K13: Down hole monitoring cabinet | L13: Cellar deck | M13: AQ200 | N13: AQ200 | O13: 1000 | P13: 800 | Q13: 2000 | R13: =(O13*P13)/1000000 -> 0.8 | U13: PERM | V13: 0.15 | W13: 300 | X13: =W13*(1+V13) -> 345 | Z13: 326290 | AA13: 383938 | AB13: 502360
C14: R | E14: A-18LE001 | H14: - | I14: 18 | K14: Temporary Pig Receiver - Krafla LP/Central (14") | L14: Mezzanine deck | M14: AP300 | N14: AP300 CANTILEVER | O14: 6200 | P14: 400 | Q14: 400 | R14: =(O14*P14)/1000000 -> 2.48 | U14: TEMP | V14: 0.15 | W14: 6770 | X14: =W14*(1+V14) -> 7785.5 | Z14: 297399 | AA14: 369000 | AB14: 508090
C15: R | E15: A-18LE002 | H15: - | I15: 18 | K15: Temporary Pig Receiver - Krafla HP (8") | L15: Mezzanine deck | M15: AP300 | N15: AP300 CANTILEVER | O15: 5600 | P15: 400 | Q15: 400 | R15: =(O15*P15)/1000000 -> 2.24 | U15: TEMP | V15: 0.15 | W15: 6770 | X15: =W15*(1+V15) -> 7785.5 | Z15: 297399 | AA15: 369000 | AB15: 508090
C16: J | E16: A-18UX001 | H16: EI014 | I16: 18 | K16: TUTU/HTP Service Umbilical from PDQ | L16: Cellar deck | M16: AP200 | N16: AP200 | O16: 3400 | P16: 1200 | Q16: 2400 | R16: =(O16*P16)/1000000 -> 4.08 | U16: PERM | V16: 0.15 | W16: 1200 | X16: =W16*(1+V16) -> 1380 | Z16: 317143 | AA16: 378400 | AB16: 500000 | BC16: Contains only interface to subsea umbilicals for liquid only
C17: J | E17: A-18UX002 | H17: EI014 | I17: 18 | K17: TUTU/HTP Service Umbilical to Central and Krafla | L17: Cellar deck | M17: AP200 | N17: AP200 | O17: 1600 | P17: 800 | Q17: 2000 | R17: =(O17*P17)/1000000 -> 1.28 | U17: PERM | V17: 0.15 | W17: 700 | X17: =W17*(1+V17) -> 805 | Z17: 314618 | AA17: 379775 | AB17: 500000 | BC17: Contains only interface to subsea umbilicals for liquid only
C18: E | D18: EEEC | E18: A-19EC001 | H18: - | I18: 19 | K18: DEH Control Cabinet Central and Krafla LP Pipeline | L18: Mezzanine deck | M18: AQ300 | N18: HV equipment room | O18: 600 | P18: 600 | Q18: 2000 | R18: =(O18*P18)/1000000 -> 0.36 | U18: PERM | V18: 0.15 | W18: 500 | X18: 575 | Z18: 323503 | AA18: 379800 | AB18: 509200 | BC18: for the HP pipeline , to be decided on c study phase
A19: NEW | C19: E | D19: EEEC | E19: A-19EC002 | H19: - | I19: 19 | K19: DCFO Remote Control Cabinet | L19: Mezzanine deck | M19: AQ300 | N19: HV equipment room | O19: 1000 | P19: 800 | Q19: 2200 | R19: =(O19*P19)/1000000 -> 0.8 | U19: PERM | V19: 0.15 | W19: 300 | X19: 575 | Z19: 326529 | AA19: 379970 | AB19: 509400 | BC19: for the HP pipeline , to be decided on c study phase
A20: NEW | C20: E | D20: EEEC | E20: A-19EC003 | H20: - | I20: 19 | K20: UID Power Control Cabinet | L20: Cellar deck | M20: AQ200 | N20: CER 2 | O20: 1000 | P20: 800 | Q20: 2200 | R20: =(O20*P20)/1000000 -> 0.8 | U20: PERM | V20: 0.15 | W20: 400 | X20: 575 | Z20: 327292 | AA20: 383938 | AB20: 502360 | BC20: for the HP pipeline , to be decided on c study phase
A21: NEW | C21: E | D21: EEER | E21: A-19ER001 | H21: - | I21: 19 | K21: DCFO Power Unit A | L21: Mezzanine deck | M21: AQ300 | N21: HV equipment room | O21: 1000 | P21: 800 | Q21: 2200 | R21: =O21*P21/1000000 -> 0.8 | U21: PERM | V21: 0.15 | W21: 450 | X21: =W21*(1+V21) -> 517.5 | Z21: 323523 | AA21: 379970 | AB21: 509400
A22: DIFF | C22: E | D22: EEER | E22: A-19ER002 | H22: - | I22: 19 | K22: DCFO Power Unit B | L22: Mezzanine deck | M22: AQ300 | N22: HV equipment room | O22: 1000 | P22: 800 | Q22: 2200 | R22: =O22*P22/1000000 -> 0.8 | U22: PERM | V22: 0.15 | W22: 450 | X22: =W22*(1+V22) -> 517.5 | Z22: 324525 | AA22: 379970 | AB22: 509200 | AS22: 500
C23: E | D23: EEET | E23: A-19ET001 | H23: - | I23: 19 | K23: DEH Transformer Central and Krafla LP Pipeline | L23: Mezzanine deck | M23: AQ300 | N23: MV Transformer room | O23: 3000 | P23: 1700 | Q23: 3000 | R23: =(O23*P23)/1000000 -> 5.1 | U23: PERM | V23: 0.15 | W23: 8500 | X23: 9000 | Z23: 341447 | AA23: 399732 | AB23: 508535 | AS23: 5000 | BC23: for the HP pipeline , to be decided on c study phase
A24: NEW | C24: E | D24: EEEX | E24: A-19EX001 | H24: - | I24: 19 | K24: Cable Routing Cabinet | L24: Mezzanine deck | M24: AQ300 | N24: HV equipment room | O24: 1000 | P24: 800 | Q24: 2200 | R24: =(O24*P24)/1000000 -> 0.8 | U24: PERM | V24: 0.15 | W24: 300 | X24: 575 | Z24: 326529 | AA24: 379970 | AB24: 509400 | BC24: for the HP pipeline , to be decided on c study phase
C25: E | D25: EEEY | E25: A-19EY001 | H25: - | I25: 19 | K25: DEH Inductor L1 Unit Central and Krafla LP Pipeline | L25: Mezzanine deck | M25: AQ300 | N25: HV equipment room | O25: 3600 | P25: 1300 | Q25: 2700 | R25: =(O25*P25)/1000000 -> 4.68 | U25: PERM | V25: 0.15 | W25: 7200 | X25: 8280 | Z25: 335352 | AA25: 372265 | AB25: 508350 | BC25: for the HP pipeline , to be decided on c study phase
C26: E | D26: EEEY | E26: A-19EY002 | H26: - | I26: 19 | K26: DEH Capacitance C1 Unit Central and Krafla LP Pipeline | L26: Mezzanine deck | M26: AQ300 | N26: HV equipment room | O26: 3600 | P26: 1300 | Q26: 2400 | R26: =(O26*P26)/1000000 -> 4.68 | U26: PERM | V26: 0.15 | W26: 2200 | X26: 2530 | Z26: 327353 | AA26: 372262 | AB26: 508200 | BC26: for the HP pipeline , to be decided on c study phase
C27: E | D27: EEEY | E27: A-19EY003 | H27: - | I27: 19 | K27: DEH Capacitance C2 Unit Central and Krafla LP Pipeline | L27: Mezzanine deck | M27: AQ300 | N27: HV equipment room | O27: 3600 | P27: 1300 | Q27: 2400 | R27: =(O27*P27)/1000000 -> 4.68 | U27: PERM | V27: 0.15 | W27: 3800 | X27: =W27*(1+V27) -> 4370 | Z27: 340352 | AA27: 372265 | AB27: 508200 | BC27: for the HP pipeline , to be decided on c study phase
A28: NEW | C28: J | D28: EJJB | E28: A-19JQ001 | H28: CPI | I28: 19 | K28: Subsea contractor network cabinet SDPU | L28: Cellar deck | M28: AQ200 | N28: CER 2 | O28: 1000 | P28: 800 | Q28: 2200 | R28: =(O28*P28)/1000000 -> 0.8 | U28: PERM | V28: 0.15 | W28: 200 | X28: =W28*(1+V28) -> 230 | Z28: 332000 | AA28: 374740 | AB28: 502360
A29: NEW | C29: J | D29: EJJB | E29: A-19JQ002 | H29: CPI | I29: 19 | K29: Subsea contractor network cabinet SGRU A | L29: Cellar deck | M29: AQ200 | N29: CER 2 | O29: 800 | P29: 800 | Q29: 2200 | R29: =(O29*P29)/1000000 -> 0.64 | U29: PERM | V29: 0.15 | W29: 200 | X29: =W29*(1+V29) -> 230 | Z29: 332802 | AA29: 374740 | AB29: 502360
A30: NEW | C30: J | D30: EJJB | E30: A-19JQ003 | H30: CPI | I30: 19 | K30: Subsea contractor network cabinet SGRU B | L30: Cellar deck | M30: AQ200 | N30: CER 2 | O30: 800 | P30: 800 | Q30: 2200 | R30: =(O30*P30)/1000000 -> 0.64 | U30: PERM | V30: 0.15 | W30: 200 | X30: =W30*(1+V30) -> 230 | Z30: 333604 | AA30: 374740 | AB30: 502360
A31: NEW | C31: J | D31: EJJB | E31: A-19JQ004 | H31: CPI | I31: 19 | K31: Subsea contractor server cabinet SGSU | L31: Cellar deck | M31: AQ200 | N31: CER 2 | O31: 800 | P31: 800 | Q31: 2200 | R31: =(O31*P31)/1000000 -> 0.64 | U31: PERM | V31: 0.15 | W31: 200 | X31: =W31*(1+V31) -> 230 | Z31: 336010 | AA31: 374740 | AB31: 502360
A32: DIFF | C32: E | D32: EEER | E32: A-20ER001A | H32: ER007 | I32: 20 | K32: VSD Liquid Export Pump A | L32: Mezzanine deck | M32: AQ400 | N32: HV VSD room | O32: 3300 | P32: 1150 | Q32: 2400 | R32: =(O32*P32)/1000000 -> 3.795 | U32: PERM | V32: 0.15 | W32: 4500 | X32: =W32*(1+V32) -> 5175 | Z32: 333271 | AA32: 398994 | AB32: 516415 | AU32: 22Cr Duplex
A33: DIFF | C33: E | D33: EEER | E33: A-20ER001B | H33: ER007 | I33: 20 | K33: VSD Liquid Export Pump B | L33: Mezzanine deck | M33: AQ400 | N33: HV VSD room | O33: 3300 | P33: 1150 | Q33: 2400 | R33: =(O33*P33)/1000000 -> 3.795 | U33: PERM | V33: 0.15 | W33: 4500 | X33: =W33*(1+V33) -> 5175 | Z33: 333279 | AA33: 395644 | AB33: 516386 | AU33: 22Cr Duplex
C34: R | E34: A-20LE001 | H34: - | I34: 20 | K34: Temporary Pig Launcher - Liquid Export (for RFO and R113 inspection) | L34: Mezzanine deck | M34: AP300 | N34: AP300 CANTILEVER | O34: 6200 | P34: 400 | Q34: 400 | R34: =(O34*P34)/1000000 -> 2.48 | U34: TEMP | V34: 0.15 | W34: 6770 | X34: =W34*(1+V34) -> 7785.5 | Z34: 297399 | AA34: 369000 | AB34: 508090
C35: R | D35: ERPA | E35: A-20PA001A | F35: NO | G35: A-20PZ001A | H35: ER007 | I35: 20 | K35: Liquid Export Pump A | L35: Cellar deck | M35: AP200 | N35: SKID | O35: 0 | P35: 0 | Q35: 0 | R35: 0 | U35: PERM | Z35: 304000 | AA35: 399000 | AB35: 501370 | AL35: 595 | AU35: 22Cr Duplex
C36: E | D36: ERPA | E36: A-20PA001A-M01 | F36: NO | G36: A-20PZ001A | H36: ER007 | I36: 20 | K36: Liquid Export Pump A Motor | L36: Cellar deck | M36: AP200 | N36: SKID | O36: 0 | P36: 0 | Q36: 0 | R36: 0 | U36: PERM | Z36: 0 | AA36: 0 | AB36: 0 | AS36: 1065
C37: R | D37: ERPA | E37: A-20PA001B | F37: NO | G37: A-20PZ001B | H37: ER007 | I37: 20 | K37: Liquid Export Pump B | L37: Cellar deck | M37: AP200 | N37: SKID | O37: 0 | P37: 0 | Q37: 0 | R37: 0 | U37: PERM | Z37: 304000 | AA37: 393000 | AB37: 501370 | AL37: 595 | AU37: 22Cr Duplex
C38: E | D38: ERPA | E38: A-20PA001B-M01 | F38: NO | G38: A-20PZ001B | H38: ER007 | I38: 20 | K38: Liquid Export Pump B Motor | L38: Cellar deck | M38: AP200 | N38: SKID | O38: 0 | P38: 0 | Q38: 0 | R38: 0 | U38: PERM | Z38: 0 | AA38: 0 | AB38: 0 | AS38: 1065
A39: DIFF | C39: R | D39: ERPZ | E39: A-20PZ001A | F39: YES | H39: ER007 | I39: 20 | K39: Liquid Export Pump A Skid | L39: Cellar deck | M39: AP200 | N39: AP200 | O39: 8500 | P39: 2400 | Q39: 2400 | R39: =(O39*P39)/1000000 -> 20.4 | U39: PERM | V39: 0.15 | W39: 26500 | X39: =W39*(1+V39) -> 30475 | Z39: 304000 | AA39: 399000 | AB39: 501370 | AU39: 25Cr Duplex | BB39: Gas carry under percentage to be finalized in process design Noise enclosure details to be finlized | BC39: Sulzer including lube oil system. including estimate for noise enclosure(5000kg) | BD39: http://data.posccaesar.org/rdl/RDS9657917 | BE39: http://data.posccaesar.org/rdl/RDS278594 | BF39: http://data.posccaesar.org/rdl/RDS14196773
A40: DIFF | C40: R | D40: ERPZ | E40: A-20PZ001B | F40: YES | H40: ER007 | I40: 20 | K40: Liquid Export Pump B Skid | L40: Cellar deck | M40: AP200 | N40: AP200 | O40: 8500 | P40: 2400 | Q40: 2400 | R40: =(O40*P40)/1000000 -> 20.4 | U40: PERM | V40: 0.15 | W40: 26500 | X40: =W40*(1+V40) -> 30475 | Z40: 304000 | AA40: 393000 | AB40: 501370 | AU40: 25Cr Duplex | BB40: Gas carry under percentage to be finalized in process design Noise enclosure details to be finlized | BC40: Sulzer including lube oil system. including estimate for noise enclosure(5000kg) | BD40: http://data.posccaesar.org/rdl/RDS9657917 | BE40: http://data.posccaesar.org/rdl/RDS278594 | BF40: http://data.posccaesar.org/rdl/RDS14196773
A41: DIFF | C41: R | D41: ERVA | E41: A-20VA001 | H41: ER002 | I41: 20 | K41: Inlet Separator | L41: Mezzanine deck | M41: AP300 | N41: AP300,AP400 | O41: 0 | P41: 3500 | Q41: 6600 | R41: =(P41*P41)/1000000 -> 12.25 | U41: PERM | V41: 0.15 | W41: 106600 | X41: =W41*(1+V41) -> 122590 | Y41: 80000 | Z41: 301200 | AA41: 387000 | AB41: 510447.5 | AH41: FV | AI41: 100 | AJ41: -46 | AK41: 125 | AN41: 80 | AU41: P500QL2 + Alloy 625 w.o. | AV41: internals 22Cr Duplex | BB41: Slug volume uncertainty (flow assurance) Gas carry under uncertainty | BC41: SLB proposal (rev 3) , vertical 2 phase separator with hemispherical heads . (weight of internals:9000kg) | BD41: http://data.posccaesar.org/rdl/RDS9647297 | BE41: http://data.posccaesar.org/rdl/RDS2194378711 | BF41: http://data.posccaesar.org/rdl/RDS291959
C42: R | D42: ERCB | E42: A-24CB001A | F42: NO | G42: A-24XX001 | H42: ER010 | I42: 24 | K42: TEG Particle Filter | L42: Process deck | M42: AP400 | N42: SKID TEG | U42: PERM | Y42: 150 | Z42: 0 | AA42: 0 | AB42: 0 | AU42: 22Cr Duplex | BC42: Vessel with 5 microns filter elements
C43: R | D43: ERCB | E43: A-24CB001B | F43: NO | G43: A-24XX001 | H43: ER010 | I43: 24 | K43: TEG Particle Filter | L43: Process deck | M43: AP400 | N43: SKID TEG | U43: PERM | V43: 0.15 | W43: 0 | X43: 0 | Y43: 150 | AU43: 22Cr Duplex | BC43: added based on Fucntional requirements documet
C44: R | D44: ERCB | E44: A-24CB002 | F44: NO | G44: A-24XX001 | H44: ER010 | I44: 24 | K44: Activated Carbon Filter | L44: Process deck | M44: AP400 | N44: SKID TEG | U44: PERM | Y44: 10 | Z44: 0 | AA44: 0 | AB44: 0 | AU44: 22Cr Duplex
A45: DIFF | C45: R | D45: ERCJ | E45: A-24CJ001 | H45: ER006 | I45: 24 | K45: G2P Mixer 1 | L45: Process deck | M45: AP400 | N45: AP400 | O45: 1400 | P45: 700 | Q45: 700 | R45: =(O45*P45)/1000000 -> 0.98 | U45: PERM | V45: 0.15 | W45: 595 | X45: =W45*(1+V45) -> 684.25 | Z45: 314126 | AA45: 383249 | AB45: 516563 | AU45: 22Cr Duplex | BB45: Single source due to Equinor Qualification | BC45: Weight / size based on Prosep propsal for Askja UPP | BF45: http://data.posccaesar.org/rdl/RDS43167562195
A46: DIFF | C46: R | D46: ERCJ | E46: A-24CJ002 | H46: ER006 | I46: 24 | K46: G2P Mixer 2 | L46: Process deck | M46: AP400 | N46: AP400 | O46: 1400 | P46: 700 | Q46: 700 | R46: =(O46*P46)/1000000 -> 0.98 | U46: PERM | V46: 0.15 | W46: 595 | X46: =W46*(1+V46) -> 684.25 | Z46: 314263 | AA46: 384362 | AB46: 516563 | AU46: 22Cr Duplex | BB46: Single source due to Equinor Qualification | BC46: Weight / size based on Prosep propsal for Askja UPP | BF46: http://data.posccaesar.org/rdl/RDS43167562195
C47: R | D47: ERCQ | E47: A-24CQ001 | F47: NO | G47: A-24XX001 | H47: ER010 | I47: 24 | K47: 1st Stage Flash Gas Ejector | L47: Process deck | M47: AP400 | N47: SKID TEG | U47: PERM | Y47: 0 | Z47: 0 | AA47: 0 | AB47: 0 | AU47: 22Cr Duplex | BC47: Ejector
C48: R | D48: ERCQ | E48: A-24CQ002 | F48: NO | G48: A-24XX001 | H48: ER010 | I48: 24 | K48: 2nd Stage Flash Gas Ejector | L48: Process deck | M48: AP400 | N48: SKID TEG | U48: PERM | Y48: 0 | Z48: 0 | AA48: 0 | AB48: 0 | AU48: 22Cr Duplex | BC48: Ejector
C49: R | D49: ERCQ | E49: A-24CQ003 | F49: NO | G49: A-24XX001 | H49: ER010 | I49: 24 | K49: 3rd Stage Flash Gas Ejector | L49: Process deck | M49: AP400 | N49: SKID TEG | U49: PERM | V49: 0 | W49: 0 | X49: 0 | Y49: 0 | AU49: 22Cr Duplex | BC49: Ejector
C50: E | D50: EEER | E50: A-24ER001A | H50: ER018 | I50: 24 | K50: VSD G2P TEG Circulation Pump A | L50: Mezzanine deck | M50: AQ300 | N50: LV swb. room 1 | O50: 600 | P50: 800 | Q50: 2200 | R50: =(O50*P50)/1000000 -> 0.48 | U50: PERM | V50: 0.15 | W50: 300 | X50: =W50*(1+V50) -> 345 | Z50: 325393 | AA50: 380793 | AB50: 509302
C51: E | D51: EEER | E51: A-24ER001B | H51: ER018 | I51: 24 | K51: VSD G2P TEG Circulation Pump B | L51: Mezzanine deck | M51: AQ300 | N51: LV swb. room 1 | O51: 600 | P51: 800 | Q51: 2200 | R51: =(O51*P51)/1000000 -> 0.48 | U51: PERM | V51: 0.15 | W51: 300 | X51: =W51*(1+V51) -> 345 | Z51: 325395 | AA51: 386621 | AB51: 509302
C52: E | D52: EEER | E52: A-24ER002A | H52: ER010 | I52: 24 | K52: Thyristor Panel - TEG Reboiler Heater A | L52: Mezzanine deck | M52: AQ300 | N52: LV swb. room 2 | O52: 2600 | P52: 500 | Q52: 2100 | R52: =(O52*P52)/1000000 -> 1.3 | U52: PERM | V52: 0.15 | W52: 750 | X52: =W52*(1+V52) -> 862.5 | Z52: 323480 | AA52: 399743 | AB52: 509301 | BC52: Width = depth of panel . Based on Dvalin type for 520kW heater
C53: E | D53: EEER | E53: A-24ER002B | H53: ER010 | I53: 24 | K53: Thyristor Panel - TEG Reboiler Heater B | L53: Mezzanine deck | M53: AQ300 | N53: LV swb. room 2 | O53: 2600 | P53: 500 | Q53: 2100 | R53: =(O53*P53)/1000000 -> 1.3 | U53: PERM | V53: 0.15 | W53: 750 | X53: =W53*(1+V53) -> 862.5 | Z53: 324290 | AA53: 399743 | AB53: 509301 | BC53: Width = depth of panel . Based on Dvalin type for 520kW heater
C54: E | D54: ERFE | E54: A-24FE001 A | F54: NO | G54: A-24XX001 | H54: ER010 | I54: 24 | K54: TEG Reboiler Heater | L54: Process deck | M54: AP400 | N54: SKID TEG | R54: =(O54*P54)/1000000 -> 0 | U54: PERM | Y54: 0 | Z54: 0 | AA54: 0 | AB54: 0 | AQ54: 465 | AU54: 22Cr Duplex | AV54: Incoloy | BC54: Length is insertion lenght. Duty is design duty.
C55: E | D55: ERFE | E55: A-24FE001 B | F55: NO | G55: A-24XX001 | H55: ER010 | I55: 24 | K55: TEG Reboiler Heater | L55: Process deck | M55: AP400 | N55: SKID TEG | R55: =(O55*P55)/1000000 -> 0 | U55: PERM | Y55: 0 | Z55: 0 | AA55: 0 | AB55: 0 | AQ55: 465 | AU55: 22Cr Duplex | AV55: Incoloy | BC55: Length is insertion lenght. Duty is design duty.
C56: E | D56: ERFE | E56: A-24FE002 | F56: NO | G56: A-24XX001 | H56: ER010 | I56: 24 | K56: TEG Surge Drum Start Up Heater | L56: Process deck | M56: AP400 | N56: SKID TEG | R56: =(O56*P56)/1000000 -> 0 | U56: PERM | Z56: 0 | AA56: 0 | AB56: 0 | AU56: 22Cr Duplex | AV56: Incoloy
A57: DIFF | C57: R | D57: ERHA | E57: A-24HA001 | H57: ER004 | I57: 24 | K57: Gas Treatment Inlet Cooler | L57: Weather deck | M57: AP500 | N57: AP500 | O57: 17400 | P57: 1520 | Q57: 2350 | R57: =(O57*P57)/1000000 -> 26.448 | U57: PERM | V57: 0.15 | W57: 24300 | X57: =W57*(1+V57) -> 27945 | Y57: 12250 | Z57: 299579 | AA57: 384249 | AB57: 524000 | AH57: 88.54 | AI57: 88.36 | AJ57: 71.4 | AK57: 20 | AL57: 6450 | AM57: 697 | AO57: SW | AQ57: 19416 | AT57: 1026.4 | AU57: Titan shell & tubes | AV57: 25%Cr Duplex Heads | BB57: risk of changing weight due to impact of design for unmanned (type of TEMA heat exchanger) | BC57: HTRI - BEM Titanium Shell & Tubes / Duplex Heads. Tube design pressure 157 barg SW In Tempt.= 11 °C SW Out Tempt.= 35 °C | BF57: http://data.posccaesar.org/rdl/RDS419084
C58: R | D58: ERHB | E58: A-24HB001 | F58: NO | G58: A-24XX001 | H58: ER010 | I58: 24 | K58: Lean / Rich TEG Heat Exchanger 1 (Bloc) | L58: Process deck | M58: AP400 | N58: SKID TEG | R58: =(O58*P58)/1000000 -> 0 | U58: PERM | Y58: 3260 | Z58: 0 | AA58: 0 | AB58: 0 | AU58: CS frame | AV58: SS316 inlernally | BC58: Bloc Type Heat Exchanger
C59: R | D59: ERHB | E59: A-24HB002 | F59: NO | G59: A-24XX001 | H59: ER010 | I59: 24 | K59: Lean / Rich TEG Heat Exchanger 2 (Gasketed Plate) | L59: Process deck | M59: AP400 | N59: SKID TEG | U59: PERM | Y59: 30 | Z59: 0 | AA59: 0 | AB59: 0 | AU59: CS frame | AV59: Titanium plates | BC59: Gasketed Plate Heat Exchanger
C60: R | D60: ERHB | E60: A-24HB003 | F60: NO | G60: A-24XX001 | H60: ER010 | I60: 24 | K60: Lean TEG Cooler | L60: Process deck | M60: AP400 | N60: SKID TEG | U60: PERM | Y60: 30 | Z60: 0 | AA60: 0 | AB60: 0 | AU60: CS frame | AV60: Titanium plates | BC60: Gasketed Plate Heat Exchanger
C61: R | D61: ERHB | E61: A-24HB004 | F61: NO | G61: A-24XX001 | H61: ER010 | I61: 24 | K61: Overhead Condenser (Bloc type hx) | L61: Process deck | M61: AP400 | N61: SKID TEG | U61: PERM | Y61: 50 | Z61: 0 | AA61: 0 | AB61: 0 | AU61: CS frame | AV61: SS316 inlernally | BC61: Bloc type hx
C62: R | D62: ERHI | E62: A-24HI001 | F62: NO | G62: A-24XX001 | H62: ER010 | I62: 24 | K62: TEG Reboiler | L62: Process deck | M62: AP400 | N62: SKID TEG | U62: PERM | Y62: 5700 | Z62: 0 | AA62: 0 | AB62: 0 | AU62: 22Cr Duplex
C63: R | D63: ERHX | E63: A-24HX001 | F63: NO | G63: A-24XX001 | H63: ER010 | I63: 24 | K63: TEG Reflux Condenser | L63: Process deck | M63: AP400 | N63: SKID TEG | U63: PERM | Y63: 50 | Z63: 0 | AA63: 0 | AB63: 0 | AQ63: 60 | AU63: 22Cr Duplex | BC63: Installed on top of still column
C64: R | D64: ERKF | E64: A-24KF001 | F64: NO | G64: A-24XX001 | H64: ER010 | I64: 24 | K64: Stripping Gas Recycle Blower | L64: Process deck | M64: AP400 | N64: SKID TEG | U64: PERM | Y64: 10 | Z64: 0 | AA64: 0 | AB64: 0 | AU64: SS316L
C65: R | D65: ERPA | E65: A-24PA001A | F65: YES | H65: ER018 | I65: 24 | K65: G2P TEG Circulation Pump A | L65: Cellar deck | M65: AP200 | N65: AP200 | O65: 2000 | P65: 1000 | Q65: 1000 | R65: =(O65*P65)/1000000 -> 2 | U65: PERM | V65: 0.15 | W65: 1220 | X65: =W65*(1+V65) -> 1403 | Z65: 312350 | AA65: 389850 | AB65: 500110 | AL65: 5 | AU65: 22Cr Duplex | BC65: PG Flow solution / Sundstrand / Magdrive sealless pump - Rated power 30 kW | BF65: http://data.posccaesar.org/rdl/RDS14196773
C66: E | D66: ERPA | E66: A-24PA001A-M01 | F66: NO | G66: A-24PA001A | H66: ER018 | I66: 24 | K66: G2P TEG Circulation Pump A Motor | L66: Cellar deck | M66: AP200 | N66: SKID | O66: 0 | P66: 0 | Q66: 0 | R66: 0 | U66: PERM | X66: =W66*(1+V66) -> 0 | Z66: 0 | AA66: 0 | AB66: 0
C67: R | D67: ERPA | E67: A-24PA001B | F67: YES | H67: ER018 | I67: 24 | K67: G2P TEG Circulation Pump B | L67: Cellar deck | M67: AP200 | N67: AP200 | O67: 2000 | P67: 1000 | Q67: 1000 | R67: =(O67*P67)/1000000 -> 2 | U67: PERM | V67: 0.15 | W67: 1220 | X67: =W67*(1+V67) -> 1403 | Z67: 312350 | AA67: 392850 | AB67: 500110 | AL67: 5 | AU67: 22Cr Duplex | BC67: PG Flow Solution / Sundstrand / Magdrive sealless pump - Rated power 30 kW | BF67: http://data.posccaesar.org/rdl/RDS14196773
C68: E | D68: ERPA | E68: A-24PA001B-M01 | F68: NO | G68: A-24PA001B | H68: ER018 | I68: 24 | K68: G2P TEG Circulation Pump B Motor | L68: Cellar deck | M68: AP200 | N68: SKID | O68: 0 | P68: 0 | Q68: 0 | R68: 0 | U68: PERM | X68: =W68*(1+V68) -> 0 | Z68: 0 | AA68: 0 | AB68: 0
C69: R | D69: ERPB | E69: A-24PB001A | F69: NO | G69: A-24XX001 | H69: ER010 | I69: 24 | K69: TEG Circulation Pump | L69: Process deck | M69: AP400 | N69: SKID TEG | U69: PERM | Y69: 110 | Z69: 0 | AA69: 0 | AB69: 0 | AR69: 15 | AU69: 22Cr Duplex | BC69: Plunger pump skid with electric drive and resonator
C70: R | D70: ERPB | E70: A-24PB001B | F70: NO | G70: A-24XX001 | H70: ER010 | I70: 24 | K70: TEG Circulation Pump | L70: Process deck | M70: AP400 | N70: SKID TEG | U70: PERM | Y70: 110 | Z70: 0 | AA70: 0 | AB70: 0 | AR70: 15 | AU70: 22Cr Duplex | BC70: Plunger pump skid with electric drive and resonator
C71: R | D71: ERPX | E71: A-24PX001 | F71: NO | G71: A-24XX001 | H71: ER010 | I71: 24 | K71: TEG Drain Tank Pump | L71: Process deck | M71: AP400 | N71: SKID TEG | U71: PERM | Z71: 0 | AA71: 0 | AB71: 0 | AU71: 22Cr Duplex | BC71: Installed in TEG Drain Tank
C72: R | D72: ERTB | E72: A-24TB001 | F72: NO | G72: A-24XX001 | H72: ER010 | I72: 24 | K72: TEG Drain Tank ( Indeck atmospheric) | L72: Process deck | M72: AP400 | N72: SKID TEG | U72: PERM | Z72: 0 | AA72: 0 | AB72: 0 | AU72: 22Cr Duplex
C73: R | D73: ERVD | E73: A-24VD001 | F73: NO | G73: A-24XX001 | H73: ER010 | I73: 24 | K73: TEG Flash Drum | L73: Process deck | M73: AP400 | N73: SKID TEG | U73: PERM | Y73: 2700 | Z73: 0 | AA73: 0 | AB73: 0 | AU73: 22Cr Duplex
C74: R | D74: ERVE | E74: A-24VE001 | F74: NO | G74: A-24XX001 | H74: ER010 | I74: 24 | K74: TEG Stripping Column | L74: Process deck | M74: AP400 | N74: SKID TEG | U74: PERM | Y74: 50 | Z74: 0 | AA74: 0 | AB74: 0 | AU74: 22Cr Duplex
C75: R | D75: ERVE | E75: A-24VE002 | F75: NO | G75: A-24XX001 | H75: ER010 | I75: 24 | K75: TEG Still Column | L75: Process deck | M75: AP400 | N75: SKID TEG | U75: PERM | Y75: 20 | Z75: 0 | AA75: 0 | AB75: 0 | AU75: 22Cr Duplex | BC75: Installed on flange on top of reboiler vessel
A76: DIFF | C76: R | D76: ERVG | E76: A-24VG001 | H76: ER003 | I76: 24 | K76: G2P Scrubber 1 | L76: Mezzanine deck | M76: AP300 | N76: AP300,AP400 | O76: - | P76: 1700 | Q76: 4200 | R76: =(P76*P76)/1000000 -> 2.89 | U76: PERM | V76: 0.15 | W76: 28700 | X76: =W76*(1+V76) -> 33005 | Z76: 310150 | AA76: 383250 | AB76: 509790 | AH76: 157 | AI76: FV | AJ76: -46 | AK76: 110 | AU76: P500QL2 + Alloy 625 w.o. | AV76: 22%Cr Duplex (S31803) | BC76: Based on SLB proposal | BF76: http://data.posccaesar.org/rdl/RDS291959
A77: DIFF | C77: R | D77: ERVG | E77: A-24VG002 | H77: ER003 | I77: 24 | K77: G2P Scrubber 2 | L77: Mezzanine deck | M77: AP300 | N77: AP300,AP400 | O77: - | P77: 2500 | Q77: 4400 | R77: =(P77*P77)/1000000 -> 6.25 | U77: PERM | V77: 0.15 | W77: 53300 | X77: =W77*(1+V77) -> 61295 | Z77: 310150 | AA77: 387500 | AB77: 509790 | AH77: 157 | AI77: FV | AJ77: -46 | AK77: 110 | AU77: P500QL2 + Alloy 625 w.o. | AV77: 22%Cr Duplex (S31803) | BB77: FDR requirement for Liquid carry over /K value | BC77: Based on SLB proposal | BF77: http://data.posccaesar.org/rdl/RDS291959
C78: R | D78: ERVG | E78: A-24VG003 | F78: NO | G78: A-24XX001 | H78: ER010 | I78: 24 | K78: Overhead Reciever | L78: Process deck | M78: AP400 | N78: SKID TEG | U78: PERM | Y78: 150 | Z78: 0 | AA78: 0 | AB78: 0 | AU78: 22Cr Duplex
C79: R | D79: ERVL | E79: A-24VL001 | F79: NO | G79: A-24XX001 | H79: ER010 | I79: 24 | K79: TEG Surge Drum | L79: Process deck | M79: AP400 | N79: SKID TEG | U79: PERM | Y79: 8900 | Z79: 0 | AA79: 0 | AB79: 0 | AU79: 22Cr Duplex
C80: R | D80: ERXR | E80: A-24XR001 | F80: NO | G80: A-24XX001 | H80: ER010 | I80: 24 | K80: TEG Chemical Injection | L80: Process deck | M80: AP400 | N80: SKID TEG | U80: PERM | Y80: 150 | Z80: 0 | AA80: 0 | AB80: 0
A81: DIFF | C81: R | D81: ERXX | E81: A-24XX001 | F81: YES | H81: ER010 | I81: 24 | K81: TEG Regeneration Package | L81: Cellar deck | M81: AP200 AP300 | N81: SKID AP200,AP300 | O81: 13000 | P81: 5000 | Q81: 11000 | R81: =O81*P81/10^6 -> 65 | U81: PERM | V81: 0.15 | W81: 60000 | X81: =W81*(1+V81) -> 69000 | Y81: 13000 | Z81: 286178 | AA81: 376775 | AB81: 502364 | AU81: 22Cr Duplex | BB81: weight accuracy due to difference between vendor proposals Open process design maturity items | BC81: Based on the Kanfa proposal for Askja UPP, Size adjusted to fit layout | BF81: http://data.posccaesar.org/rdl/RDS269279
C82: R | E82: A-26LE001 | I82: 26 | K82: Temporary Pig Launcher - Gas Lift | L82: Mezzanine deck | M82: AP300 | N82: AP300 CANTILEVER | O82: 8000 | P82: 600 | Q82: 600 | R82: =(O82*P82)/1000000 -> 4.8 | U82: TEMP | V82: 0.15 | W82: 7250 | X82: =W82*(1+V82) -> 8337.5 | Z82: 297399 | AA82: 369000 | AB82: 508090
C83: E | D83: EEEC | E83: A-27EC001 | H83: ER001 | I83: 27 | K83: AMB Control Cabinet 1st Stage Compressor | L83: Process deck | M83: AQ300 | N83: LV swb. room 1 | O83: 3000 | P83: 800 | Q83: 2200 | R83: =(O83*P83)/1000000 -> 2.4 | U83: PERM | V83: 0.15 | W83: 1600 | X83: =W83*(1+V83) -> 1840 | Z83: 324572 | AA83: 402744 | AB83: 509265
C84: E | D84: EEEC | E84: A-27EC002 | H84: ER001 | I84: 27 | K84: AMB Control Cabinet 2nd Stage Compressor | L84: Process deck | M84: AQ300 | N84: LV swb. room 1 | O84: 3000 | P84: 800 | Q84: 2200 | R84: =(O84*P84)/1000000 -> 2.4 | U84: PERM | V84: 0.15 | W84: 1600 | X84: =W84*(1+V84) -> 1840 | Z84: 328372 | AA84: 403528 | AB84: 509265
C85: E | D85: EEER | E85: A-27ER001 | H85: EE004 | I85: 27 | K85: VSD 1st Stage Compressor | L85: Process deck | M85: AQ400 | N85: HV VSD room | O85: 13600 | P85: 1600 | Q85: 2800 | R85: =(O85*P85)/1000000 -> 21.76 | U85: PERM | V85: 0.15 | W85: 12000 | X85: =W85*(1+V85) -> 13800 | Z85: 325808 | AA85: 394800 | AB85: 516650 | AS85: 12000 | BC85: ABB ACS 5069-W3B-D5 (Same size as ÅSC). Water cooled
C86: E | D86: EEER | E86: A-27ER002 | H86: EE004 | I86: 27 | K86: VSD 2nd Stage Compressor | L86: Process deck | M86: AQ400 | N86: HV VSD room | O86: 13600 | P86: 1600 | Q86: 2800 | R86: =(O86*P86)/1000000 -> 21.76 | U86: PERM | V86: 0.15 | W86: 12000 | X86: =W86*(1+V86) -> 13800 | Z86: 328008 | AA86: 400500 | AB86: 515250 | AS86: 12000 | BC86: ABB ACS 5069-W3B-D5 (Same size as ÅSC). Water cooled
C87: E | D87: EEER | E87: A-27ER003 | H87: ER020 | I87: 27 | K87: Thyristor Control Panel for 27FE001 | L87: Mezzanine deck | M87: AQ300 | N87: LV swb. room 1 | O87: 2000 | P87: 1800 | Q87: 500 | R87: =(O87*P87)/1000000 -> 3.6 | U87: PERM | V87: 0.15 | W87: 500 | X87: =W87*(1+V87) -> 575 | Z87: 323963 | AA87: 397121 | AB87: 509200 | BC87: Located in Main LV Switcboard room. Exheat provided info
C88: E | D88: EEER | E88: A-27ER004A | H88: ER018 | I88: 27 | K88: VSD 1st Stage Compressor Suction Scrubber Pump A | L88: Mezzanine deck | M88: AQ300 | N88: LV swb. room 1 | O88: 600 | P88: 800 | Q88: 2200 | R88: =(P88*P88)/1000000 -> 0.64 | U88: PERM | V88: 0.15 | W88: 300 | X88: =W88*(1+V88) -> 345 | Z88: 323480 | AA88: 399127 | AB88: 509301
C89: E | D89: EEER | E89: A-27ER004B | H89: ER018 | I89: 27 | K89: VSD 1st Stage Compressor Suction Scrubber Pump B | L89: Mezzanine deck | M89: AQ300 | N89: LV swb. room 1 | O89: 600 | P89: 800 | Q89: 2200 | R89: =(P89*P89)/1000000 -> 0.64 | U89: PERM | V89: 0.15 | W89: 300 | X89: =W89*(1+V89) -> 345 | Z89: 324290 | AA89: 399127 | AB89: 509301
A90: DIFF | C90: E | D90: EEET | E90: A-27ET001 | H90: EE004 | I90: 27 | K90: 100/2 kV Transformer 18 MVA 1st Stage Compressor | L90: Process deck | M90: AQ400 | N90: HV Transformer room | O90: 5000 | P90: 4000 | Q90: 5000 | R90: =(O90*P90)/1000000 -> 20 | U90: PERM | V90: 0.15 | W90: 42000 | X90: =W90*(1+V90) -> 48300 | Y90: 12000 | Z90: 340390 | AA90: 393490 | AB90: 516220 | AS90: 13000 | BC90: ABB transf 65000/6x1920V. 7-winding made for ACS5000 VSD. Water cooled
A91: DIFF | C91: E | D91: EEET | E91: A-27ET002 | H91: EE004 | I91: 27 | K91: 100/2 kV Transformer 18 MVA 2nd Stage Compressor | L91: Process deck | M91: AQ400 | N91: HV Transformer room | O91: 5000 | P91: 4000 | Q91: 5000 | R91: =(O91*P91)/1000000 -> 20 | U91: PERM | V91: 0.15 | W91: 42000 | X91: =W91*(1+V91) -> 48300 | Y91: 12000 | Z91: 340390 | AA91: 399990 | AB91: 516220 | AS91: 13000 | BC91: ABB transf 65000/6x1920V 7-winding made for ACS5000 VSD Water cooled
A92: DIFF | C92: R | D92: ERFE | E92: A-27FE001 | H92: ER020 | I92: 27 | K92: Backflow Heater | L92: Process deck | M92: AP400 | N92: AP400 | O92: 4000 | P92: 830 | Q92: 1500 | R92: =(O92*P92)/1000000 -> 3.32 | U92: PERM | V92: 0.15 | W92: 3174 | X92: =W92*(1+V92) -> 3650.1 | Z92: 308179 | AA92: 399279 | AB92: 514700 | AH92: 185 | AJ92: -46 | AK92: 150 | AS92: 540 | AU92: 22Cr Duplex | BC92: Based on previous stduy input (Exheat provided info. ) | BF92: http://data.posccaesar.org/rdl/RDS14070475
A93: DIFF | C93: R | D93: ERHA | E93: A-27HA001 | H93: ER004 | I93: 27 | K93: 1st Stage Compressor Suction Cooler | L93: Weather deck | M93: AP500 | N93: AP500 | O93: 15885 | P93: 1750 | Q93: 2610 | R93: =(O93*P93)/1000000 -> 27.79875 | U93: PERM | V93: 0.15 | W93: 25610 | X93: =W93*(1+V93) -> 29451.5 | Y93: 16450 | Z93: 300609 | AA93: 380499 | AB93: 524000 | AH93: 33.636 | AI93: 33.364 | AJ93: 84.5 | AK93: 20 | AL93: 14028 | AM93: 817 | AO93: SW | AQ93: 22801 | AT93: 1246 | AU93: Titan shell & tubes | AV93: 25%Cr Duplex Heads | BB93: risk of changing weight due to impact of design for unmanned (type of TEMA heat exchanger) | BC93: HTRI - BEM Titanium Shell & Tubes / Duplex Heads. Tube design pressure 100 barg SW In Tempt.= 11 °C SW Out Tempt.= 35 °C | BF93: http://data.posccaesar.org/rdl/RDS419084
A94: NEW | C94: R | D94: ERHA | E94: A-27HA002 | H94: ER004 | I94: 27 | K94: Gas Export Cooler | L94: Process deck | M94: AP400 | N94: AP400 | O94: 8600 | P94: 920 | Q94: 1070 | R94: =(O94*P94)/1000000 -> 7.912 | U94: PERM | V94: 0.15 | W94: 5890 | X94: =W94*(1+V94) -> 6773.5 | Y94: 1260 | AH94: 163.5 | AI94: 163.05 | AJ94: 137.7 | AK94: 90 | AL94: 1218 | AM94: 188 | AO94: SW | AQ94: 5204 | AT94: 62.7 | AU94: Titan shell & tubes | AV94: 25%Cr Duplex Heads | BB94: Uncertainty on process design/duty/size/weight | BC94: Current sizing is based on Case A from TN C232-AI-P-RA-00010 Rev 02 SW In Tempt.= 10 °C SW Out Tempt.= 34.15 °C Gas Flow Rate = 135216 kg/hr | BF94: http://data.posccaesar.org/rdl/RDS419084
C95: R | D95: ERHB | E95: A-27HB001 | H95: ER009 | I95: 27 | K95: VSD External Cooler (1st Stage Compressor VSD) | L95: Process deck | M95: AP400 | N95: AP400 | O95: 1000 | P95: 500 | Q95: 1000 | R95: =(O95*P95)/1000000 -> 0.5 | U95: PERM | V95: 0.15 | W95: 1250 | X95: =W95*(1+V95) -> 1437.5 | Z95: 319045 | AA95: 391536 | AB95: 506925 | AU95: Titanium Plate | AV95: CS Frame | BC95: Based on ABB input | BF95: http://data.posccaesar.org/rdl/RDS441674
C96: R | D96: ERHB | E96: A-27HB002 | H96: ER009 | I96: 27 | K96: VSD External Cooler (2nd Stage Compressor VSD) | L96: Process deck | M96: AP400 | N96: AP400 | O96: 1000 | P96: 500 | Q96: 1000 | R96: =(O96*P96)/1000000 -> 0.5 | U96: PERM | V96: 0.15 | W96: 1250 | X96: =W96*(1+V96) -> 1437.5 | Z96: 319045 | AA96: 396637 | AB96: 506925 | AU96: Titanium Plate | AV96: CS Frame | BC96: Based on ABB input | BF96: http://data.posccaesar.org/rdl/RDS441674
C97: J | D97: EJJX | E97: A-27JX001 | H97: EI002 | I97: 27 | K97: Fiscal Gas Export Metering | L97: Process deck | M97: AP400 | N97: AP400 | O97: 9200 | P97: 1500 | Q97: 2000 | R97: =(O97*P97)/1000000 -> 13.8 | U97: PERM | V97: 0.15 | W97: 4000 | X97: =W97*(1+V97) -> 4600 | Z97: 297388 | AA97: 374219 | AB97: 514100
C98: J | D98: EJJX | E98: A-27JX002 | H98: EI002 | I98: 27 | K98: Fiscal Gas Export Metering Analyser | L98: Process deck | M98: AP400 | N98: AP400 CANTILEVER | O98: 2500 | P98: 2500 | Q98: 2500 | R98: =(O98*P98)/1000000 -> 6.25 | U98: PERM | V98: 0.15 | W98: 2500 | X98: =W98*(1+V98) -> 2875 | Z98: 312339 | AA98: 373470 | AB98: 514000
C99: R | D99: ERKA | E99: A-27KA001 | F99: NO | G99: A-27KZ001 | H99: ER001 | I99: 27 | K99: 1st Stage Compressor | L99: Weather deck | M99: AP500 | N99: SKID | O99: 0 | P99: 0 | Q99: 0 | R99: 0 | U99: PERM | X99: =W99*(1+V99) -> 0 | Z99: 0 | AA99: 0 | AB99: 0
C100: E | E100: A-27KA001-M01 | F100: NO | G100: A-27KZ001 | H100: ER001 | I100: 27 | K100: 1st Stage Compressor Motor | L100: Weather deck | M100: AP500 | N100: SKID | O100: 0 | P100: 0 | Q100: 0 | R100: 0 | U100: PERM | X100: =W100*(1+V100) -> 0 | Z100: 0 | AA100: 0 | AB100: 0
C101: R | D101: ERKA | E101: A-27KA002 | F101: NO | G101: A-27KZ002 | H101: ER001 | I101: 27 | K101: 2nd Stage Compressor | L101: Weather deck | M101: AP500 | N101: SKID | O101: 0 | P101: 0 | Q101: 0 | R101: 0 | U101: PERM | X101: =W101*(1+V101) -> 0 | Z101: 0 | AA101: 0 | AB101: 0
...

Sheet Reference Info
B2: Aibel
B3: EQUIPMENT LIST | N3: Page No.: 2 of 10
N4: Date: 24.03.2021
B5: Document No.: C232-AI-R-LA-00001 | N5: Rev. No.: 02
C7: Preliminary only
B8: Preliminary Package List | D8: Resp | G8: Main Area Codes | H8: Main Area Description | K8: Module
B9: Pck no. | C9: Package Description | D9: Aibel | E9: Company
B10: ER001 | C10: Gas Compressor Package | E10: X | G10: AF000 | H10: Flare tower
B11: ER002 | C11: Inlet Separator Package | D11: X | G11: AK000 | H11: Crane
B12: ER003 | C12: Gas Scrubbers | D12: X | G12: AJ000 | H12: Jacket
B13: ER004 | C13: Shell & Tube Exchangers | D13: X | G13: AP110 | H13: Stair tower - west | K13: Process Module
B14: ER005 | C14: Open | D14: X | G14: AQ110 | H14: Stair tower - east | K14: Utility Module
B15: ER006 | C15: G2P Mixer Package | D15: X | G15: AP100 | H15: W2W deck | K15: Process Module
B16: ER007 | C16: Liquid Export Pumps | D16: X | G16: AP200 | H16: Cellar deck | K16: Process Module
B17: ER008 | C17: Positive Displacement Pumps (HOLD) | D17: X | G17: AP300 | H17: Mezzanine deck | K17: Process Module
B18: ER009 | C18: Plate and Frame Exchangers | D18: X | G18: AP400 | H18: Process deck | K18: Process Module
B19: ER010 | C19: TEG Regeneration | D19: X | G19: AP500 | H19: Weather deck | K19: Process Module
B20: ER011 | C20: Seawater Lift Pumps | D20: X | G20: AQ200 | H20: Cellar deck | K20: Utility Module
B21: ER012 | C21: Seawater Filtration Pck | D21: X | G21: AQ300 | H21: Mezzanine deck | K21: Utility Module
B22: ER013 | C22: Misc Pressure Vessels | D22: X | G22: AQ400 | H22: Process deck | K22: Utility Module
B23: ER014 | C23: Misc Atmospheric Tanks | D23: X
B24: ER015 | C24: Electro Chlorination Package | D24: X
B25: ER016 | C25: Pedestal Crane | D25: X | E25: X
B26: ER017 | C26: Misc. Lifting / Material Handling Equipment | D26: X
B27: ER018 | C27: Misc Centrifugal Pumps | D27: X
B28: ER019 | C28: Relif Vent Tip Pck incl. Ignition Pck | D28: X
B29: ER020 | C29: Electric Heaters | D29: X
B30: ES001 | C30: Escape Chute | D30: X
B31: EE001 | C31: HV Tranformers | D31: X
B32: EE002 | C32: HV/LV Switchgear | D32: X
B33: EE003 | C33: UPS Package | D33: X
B34: EE007 | C34: VSD Package - include in mechanical/HVAC packages? | D34: X
B35: EI101 | C35: SAS Package | D35: X | E35: X
B36: ET001 | C36: Telecom Equipment | D36: X
B37: EH001 | C37: HVAC Equipment | D37: X
B38: ES002 | C38: Misc Firefighting Equipment | D38: X
B39: EI106 | C39: Drones/Robotics
B40: EE006 | C40: Nav Aid | D40: X
B41: EE005 | C41: LV Distribution Boards | D41: X
B42: EE004 | C42: LV Transformers | D42: X
B43: EI001 | C43: Hydraulic Power Unit
B44: EI002 | C44: Fiscal Metering and Analysis
B45: EI102 | C45: Condition & Performance Monitoring
B46: EI103 | C46: Vibration Monitoring
B47: EI104 | C47: Field Device Management
B48: EI105 | C48: Dynamic Simulator Model
B49: EI003 | C49: Process Analysis
B50: BN001 | C50: Bridge Bearing & Monitoring system
B51: EI004 | C51: Level Instruments
B52: EI007 | C52: Electrical Actuators
B53: EI005 | C53: Flow measurement
B54: EI006 | C54: Sand Detection
... B60: EI013 | C60: Valve Condition Monitoring

Sheet Summary
B2: Summary per area
B3: Area | C3: Description | D3: Footprint PERM (m2) | E3: Footprint FUT/ TEMP (m2) | F3: Footprint total (m2) | G3: Net Dry Weight PERM (kg) | H3: Net Dry Weight FUT/ TEMP (kg) | I3: Net Dry Weight total (kg) | J3: Gross Dry Weight PERM (kg) | K3: Gross Dry Weight FUT/ TEMP (kg) | L3: Gross Dry Weight total (kg) | M3: Content Weight PERM (kg) | N3: Content Weight FUT/ TEMP (kg) | O3: Content Weight total (kg)
B4: Cellar deck | D4: =SUMIFS(MEL!R:R,MEL!R:R,"<>",MEL!$L:$L,$B4,MEL!$U:$U,"PERM") -> 340.8906 | E4: =SUMIFS(MEL!R:R,MEL!R:R,"<>",MEL!$L:$L,$B4,MEL!$U:$U,"TEMP")+SUMIFS(MEL!R:R,MEL!R:R,"<>",MEL!$L:$L,$B4,MEL!$U:$U,"FUT") -> 29.247344 | F4: =D4+E4 -> 370.13794 | G4: =SUMIFS(MEL!W:W,MEL!W:W,"<>",MEL!$L:$L,$B4,MEL!$U:$U,"PERM") -> 291420 | H4: =SUMIFS(MEL!W:W,MEL!W:W,"<>",MEL!$L:$L,$B4,MEL!$U:$U,"TEMP")+SUMIFS(MEL!W:W,MEL!W:W,"<>",MEL!$L:$L,$B4,MEL!$U:$U,"FUT") -> 21200 | I4: =G4+H4 -> 312620 | J4: =SUMIFS(MEL!X:X,MEL!X:X,"<>",MEL!$L:$L,$B4,MEL!$U:$U,"PERM") -> 335242 | K4: =SUMIFS(MEL!X:X,MEL!X:X,"<>",MEL!$L:$L,$B4,MEL!$U:$U,"TEMP")+SUMIFS(MEL!X:X,MEL!X:X,"<>",MEL!$L:$L,$B4,MEL!$U:$U,"FUT") -> 24380 | L4: =J4+K4 -> 359622 | M4: =SUMIFS(MEL!Y:Y,MEL!Y:Y,"<>",MEL!$L:$L,$B4,MEL!$U:$U,"PERM") -> 90300 | N4: =SUMIFS(MEL!Y:Y,MEL!Y:Y,"<>",MEL!$L:$L,$B4,MEL!$U:$U,"TEMP")+SUMIFS(MEL!Y:Y,MEL!Y:Y,"<>",MEL!$L:$L,$B4,MEL!$U:$U,"FUT") -> 0 | O4: =M4+N4 -> 90300
B5: Mezzanine deck | D5: =SUMIFS(MEL!R:R,MEL!R:R,"<>",MEL!$L:$L,$B5,MEL!$U:$U,"PERM") -> 211.5748 | E5: =SUMIFS(MEL!R:R,MEL!R:R,"<>",MEL!$L:$L,$B5,MEL!$U:$U,"TEMP")+SUMIFS(MEL!R:R,MEL!R:R,"<>",MEL!$L:$L,$B5,MEL!$U:$U,"FUT") -> 45.7356 | F5: =D5+E5 -> 257.3104 | G5: =SUMIFS(MEL!W:W,MEL!W:W,"<>",MEL!$L:$L,$B5,MEL!$U:$U,"PERM") -> 413971.74 | H5: =SUMIFS(MEL!W:W,MEL!W:W,"<>",MEL!$L:$L,$B5,MEL!$U:$U,"TEMP")+SUMIFS(MEL!W:W,MEL!W:W,"<>",MEL!$L:$L,$B5,MEL!$U:$U,"FUT") -> 58800 | I5: =G5+H5 -> 472771.74 | J5: =SUMIFS(MEL!X:X,MEL!X:X,"<>",MEL!$L:$L,$B5,MEL!$U:$U,"PERM") -> 475177.5 | K5: =SUMIFS(MEL!X:X,MEL!X:X,"<>",MEL!$L:$L,$B5,MEL!$U:$U,"TEMP")+SUMIFS(MEL!X:X,MEL!X:X,"<>",MEL!$L:$L,$B5,MEL!$U:$U,"FUT") -> 67620 | L5: =J5+K5 -> 542797.5 | M5: =SUMIFS(MEL!Y:Y,MEL!Y:Y,"<>",MEL!$L:$L,$B5,MEL!$U:$U,"PERM") -> 84700 | N5: =SUMIFS(MEL!Y:Y,MEL!Y:Y,"<>",MEL!$L:$L,$B5,MEL!$U:$U,"TEMP")+SUMIFS(MEL!Y:Y,MEL!Y:Y,"<>",MEL!$L:$L,$B5,MEL!$U:$U,"FUT") -> 0 | O5: =M5+N5 -> 84700
B6: Process deck | D6: =SUMIFS(MEL!R:R,MEL!R:R,"<>",MEL!$L:$L,$B6,MEL!$U:$U,"PERM") -> 210.622 | E6: =SUMIFS(MEL!R:R,MEL!R:R,"<>",MEL!$L:$L,$B6,MEL!$U:$U,"TEMP")+SUMIFS(MEL!R:R,MEL!R:R,"<>",MEL!$L:$L,$B6,MEL!$U:$U,"FUT") -> 6.73 | F6: =D6+E6 -> 217.352 | G6: =SUMIFS(MEL!W:W,MEL!W:W,"<>",MEL!$L:$L,$B6,MEL!$U:$U,"PERM") -> 231324 | H6: =SUMIFS(MEL!W:W,MEL!W:W,"<>",MEL!$L:$L,$B6,MEL!$U:$U,"TEMP")+SUMIFS(MEL!W:W,MEL!W:W,"<>",MEL!$L:$L,$B6,MEL!$U:$U,"FUT") -> 5400 | I6: =G6+H6 -> 236724 | J6: =SUMIFS(MEL!X:X,MEL!X:X,"<>",MEL!$L:$L,$B6,MEL!$U:$U,"PERM") -> 265275.1 | K6: =SUMIFS(MEL!X:X,MEL!X:X,"<>",MEL!$L:$L,$B6,MEL!$U:$U,"TEMP")+SUMIFS(MEL!X:X,MEL!X:X,"<>",MEL!$L:$L,$B6,MEL!$U:$U,"FUT") -> 6210 | L6: =J6+K6 -> 271485.1 | M6: =SUMIFS(MEL!Y:Y,MEL!Y:Y,"<>",MEL!$L:$L,$B6,MEL!$U:$U,"PERM") -> 66933.61 | N6: =SUMIFS(MEL!Y:Y,MEL!Y:Y,"<>",MEL!$L:$L,$B6,MEL!$U:$U,"TEMP")+SUMIFS(MEL!Y:Y,MEL!Y:Y,"<>",MEL!$L:$L,$B6,MEL!$U:$U,"FUT") -> 0 | O6: =M6+N6 -> 66933.61
B7: Weather deck | D7: =SUMIFS(MEL!R:R,MEL!R:R,"<>",MEL!$L:$L,$B7,MEL!$U:$U,"PERM") -> 118.85965 | E7: =SUMIFS(MEL!R:R,MEL!R:R,"<>",MEL!$L:$L,$B7,MEL!$U:$U,"TEMP")+SUMIFS(MEL!R:R,MEL!R:R,"<>",MEL!$L:$L,$B7,MEL!$U:$U,"FUT") -> 47.567564 | F7: =D7+E7 -> 166.42721 | G7: =SUMIFS(MEL!W:W,MEL!W:W,"<>",MEL!$L:$L,$B7,MEL!$U:$U,"PERM") -> 201698 | H7: =SUMIFS(MEL!W:W,MEL!W:W,"<>",MEL!$L:$L,$B7,MEL!$U:$U,"TEMP")+SUMIFS(MEL!W:W,MEL!W:W,"<>",MEL!$L:$L,$B7,MEL!$U:$U,"FUT") -> 42020 | I7: =G7+H7 -> 243718 | J7: =SUMIFS(MEL!X:X,MEL!X:X,"<>",MEL!$L:$L,$B7,MEL!$U:$U,"PERM") -> 231952.7 | K7: =SUMIFS(MEL!X:X,MEL!X:X,"<>",MEL!$L:$L,$B7,MEL!$U:$U,"TEMP")+SUMIFS(MEL!X:X,MEL!X:X,"<>",MEL!$L:$L,$B7,MEL!$U:$U,"FUT") -> 48323 | L7: =J7+K7 -> 280275.7 | M7: =SUMIFS(MEL!Y:Y,MEL!Y:Y,"<>",MEL!$L:$L,$B7,MEL!$U:$U,"PERM") -> 28700 | N7: =SUMIFS(MEL!Y:Y,MEL!Y:Y,"<>",MEL!$L:$L,$B7,MEL!$U:$U,"TEMP")+SUMIFS(MEL!Y:Y,MEL!Y:Y,"<>",MEL!$L:$L,$B7,MEL!$U:$U,"FUT") -> 0 | O7: =M7+N7 -> 28700
B8: Stair tower east | D8: =SUMIFS(MEL!R:R,MEL!R:R,"<>",MEL!$L:$L,$B8,MEL!$U:$U,"PERM") -> 0 | E8: =SUMIFS(MEL!R:R,MEL!R:R,"<>",MEL!$L:$L,$B8,MEL!$U:$U,"TEMP")+SUMIFS(MEL!R:R,MEL!R:R,"<>",MEL!$L:$L,$B8,MEL!$U:$U,"FUT") -> 2.94 | F8: =D8+E8 -> 2.94 | G8: =SUMIFS(MEL!W:W,MEL!W:W,"<>",MEL!$L:$L,$B8,MEL!$U:$U,"PERM") -> 0 | H8: =SUMIFS(MEL!W:W,MEL!W:W,"<>",MEL!$L:$L,$B8,MEL!$U:$U,"TEMP")+SUMIFS(MEL!W:W,MEL!W:W,"<>",MEL!$L:$L,$B8,MEL!$U:$U,"FUT") -> 1200 | I8: =G8+H8 -> 1200 | J8: =SUMIFS(MEL!X:X,MEL!X:X,"<>",MEL!$L:$L,$B8,MEL!$U:$U,"PERM") -> 0 | K8: =SUMIFS(MEL!X:X,MEL!X:X,"<>",MEL!$L:$L,$B8,MEL!$U:$U,"TEMP")+SUMIFS(MEL!X:X,MEL!X:X,"<>",MEL!$L:$L,$B8,MEL!$U:$U,"FUT") -> 1380 | L8: =J8+K8 -> 1380 | M8: =SUMIFS(MEL!Y:Y,MEL!Y:Y,"<>",MEL!$L:$L,$B8,MEL!$U:$U,"PERM") -> 0 | N8: =SUMIFS(MEL!Y:Y,MEL!Y:Y,"<>",MEL!$L:$L,$B8,MEL!$U:$U,"TEMP")+SUMIFS(MEL!Y:Y,MEL!Y:Y,"<>",MEL!$L:$L,$B8,MEL!$U:$U,"FUT") -> 0 | O8: =M8+N8 -> 0
B9: W2W deck | D9: =SUMIFS(MEL!R:R,MEL!R:R,"<>",MEL!$L:$L,$B9,MEL!$U:$U,"PERM") -> 4 | E9: =SUMIFS(MEL!R:R,MEL!R:R,"<>",MEL!$L:$L,$B9,MEL!$U:$U,"TEMP")+SUMIFS(MEL!R:R,MEL!R:R,"<>",MEL!$L:$L,$B9,MEL!$U:$U,"FUT") -> 0 | F9: =D9+E9 -> 4 | G9: =SUMIFS(MEL!W:W,MEL!W:W,"<>",MEL!$L:$L,$B9,MEL!$U:$U,"PERM") -> 2800 | H9: =SUMIFS(MEL!W:W,MEL!W:W,"<>",MEL!$L:$L,$B9,MEL!$U:$U,"TEMP")+SUMIFS(MEL!W:W,MEL!W:W,"<>",MEL!$L:$L,$B9,MEL!$U:$U,"FUT") -> 0 | I9: =G9+H9 -> 2800 | J9: =SUMIFS(MEL!X:X,MEL!X:X,"<>",MEL!$L:$L,$B9,MEL!$U:$U,"PERM") -> 3220 | K9: =SUMIFS(MEL!X:X,MEL!X:X,"<>",MEL!$L:$L,$B9,MEL!$U:$U,"TEMP")+SUMIFS(MEL!X:X,MEL!X:X,"<>",MEL!$L:$L,$B9,MEL!$U:$U,"FUT") -> 0 | L9: =J9+K9 -> 3220 | M9: =SUMIFS(MEL!Y:Y,MEL!Y:Y,"<>",MEL!$L:$L,$B9,MEL!$U:$U,"PERM") -> 7500 | N9: =SUMIFS(MEL!Y:Y,MEL!Y:Y,"<>",MEL!$L:$L,$B9,MEL!$U:$U,"TEMP")+SUMIFS(MEL!Y:Y,MEL!Y:Y,"<>",MEL!$L:$L,$B9,MEL!$U:$U,"FUT") -> 0 | O9: =M9+N9 -> 7500
B10: Flare tower | D10: =SUMIFS(MEL!R:R,MEL!R:R,"<>",MEL!$L:$L,$B10,MEL!$U:$U,"PERM") -> 1.324844 | E10: =SUMIFS(MEL!R:R,MEL!R:R,"<>",MEL!$L:$L,$B10,MEL!$U:$U,"TEMP")+SUMIFS(MEL!R:R,MEL!R:R,"<>",MEL!$L:$L,$B10,MEL!$U:$U,"FUT") -> 0 | F10: =D10+E10 -> 1.324844 | G10: =SUMIFS(MEL!W:W,MEL!W:W,"<>",MEL!$L:$L,$B10,MEL!$U:$U,"PERM") -> 3265 | H10: =SUMIFS(MEL!W:W,MEL!W:W,"<>",MEL!$L:$L,$B10,MEL!$U:$U,"TEMP")+SUMIFS(MEL!W:W,MEL!W:W,"<>",MEL!$L:$L,$B10,MEL!$U:$U,"FUT") -> 0 | I10: =G10+H10 -> 3265 | J10: =SUMIFS(MEL!X:X,MEL!X:X,"<>",MEL!$L:$L,$B10,MEL!$U:$U,"PERM") -> 3754.75 | K10: =SUMIFS(MEL!X:X,MEL!X:X,"<>",MEL!$L:$L,$B10,MEL!$U:$U,"TEMP")+SUMIFS(MEL!X:X,MEL!X:X,"<>",MEL!$L:$L,$B10,MEL!$U:$U,"FUT") -> 0 | L10: =J10+K10 -> 3754.75 | M10: =SUMIFS(MEL!Y:Y,MEL!Y:Y,"<>",MEL!$L:$L,$B10,MEL!$U:$U,"PERM") -> 0 | N10: =SUMIFS(MEL!Y:Y,MEL!Y:Y,"<>",MEL!$L:$L,$B10,MEL!$U:$U,"TEMP")+SUMIFS(MEL!Y:Y,MEL!Y:Y,"<>",MEL!$L:$L,$B10,MEL!$U:$U,"FUT") -> 0 | O10: =M10+N10 -> 0
B11: Crane | D11: =SUMIFS(MEL!R:R,MEL!R:R,"<>",MEL!$L:$L,$B11,MEL!$U:$U,"PERM") -> 220.48 | E11: =SUMIFS(MEL!R:R,MEL!R:R,"<>",MEL!$L:$L,$B11,MEL!$U:$U,"TEMP")+SUMIFS(MEL!R:R,MEL!R:R,"<>",MEL!$L:$L,$B11,MEL!$U:$U,"FUT") -> 0 | F11: =D11+E11 -> 220.48 | G11: =SUMIFS(MEL!W:W,MEL!W:W,"<>",MEL!$L:$L,$B11,MEL!$U:$U,"PERM") -> 169300 | H11: =SUMIFS(MEL!W:W,MEL!W:W,"<>",MEL!$L:$L,$B11,MEL!$U:$U,"TEMP")+SUMIFS(MEL!W:W,MEL!W:W,"<>",MEL!$L:$L,$B11,MEL!$U:$U,"FUT") -> 0 | I11: =G11+H11 -> 169300 | J11: =SUMIFS(MEL!X:X,MEL!X:X,"<>",MEL!$L:$L,$B11,MEL!$U:$U,"PERM") -> 194695 | K11: =SUMIFS(MEL!X:X,MEL!X:X,"<>",MEL!$L:$L,$B11,MEL!$U:$U,"TEMP")+SUMIFS(MEL!X:X,MEL!X:X,"<>",MEL!$L:$L,$B11,MEL!$U:$U,"FUT") -> 0 | L11: =J11+K11 -> 194695 | M11: =SUMIFS(MEL!Y:Y,MEL!Y:Y,"<>",MEL!$L:$L,$B11,MEL!$U:$U,"PERM") -> 0 | N11: =SUMIFS(MEL!Y:Y,MEL!Y:Y,"<>",MEL!$L:$L,$B11,MEL!$U:$U,"TEMP")+SUMIFS(MEL!Y:Y,MEL!Y:Y,"<>",MEL!$L:$L,$B11,MEL!$U:$U,"FUT") -> 0 | O11: =M11+N11 -> 0
D12: =SUMIFS(MEL!R:R,MEL!R:R,"<>",MEL!$L:$L,$B12,MEL!$U:$U,"PERM") -> 0 | E12: =SUMIFS(MEL!R:R,MEL!R:R,"<>",MEL!$L:$L,$B12,MEL!$U:$U,"TEMP")+SUMIFS(MEL!R:R,MEL!R:R,"<>",MEL!$L:$L,$B12,MEL!$U:$U,"FUT") -> 0 | F12: =D12+E12 -> 0 | G12: =SUMIFS(MEL!W:W,MEL!W:W,"<>",MEL!$L:$L,$B12,MEL!$U:$U,"PERM") -> 0 | H12: =SUMIFS(MEL!W:W,MEL!W:W,"<>",MEL!$L:$L,$B12,MEL!$U:$U,"TEMP")+SUMIFS(MEL!W:W,MEL!W:W,"<>",MEL!$L:$L,$B12,MEL!$U:$U,"FUT") -> 0 | I12: =G12+H12 -> 0 | J12: =SUMIFS(MEL!X:X,MEL!X:X,"<>",MEL!$L:$L,$B12,MEL!$U:$U,"PERM") -> 0 | K12: =SUMIFS(MEL!X:X,MEL!X:X,"<>",MEL!$L:$L,$B12,MEL!$U:$U,"TEMP")+SUMIFS(MEL!X:X,MEL!X:X,"<>",MEL!$L:$L,$B12,MEL!$U:$U,"FUT") -> 0 | L12: =J12+K12 -> 0 | M12: =SUMIFS(MEL!Y:Y,MEL!Y:Y,"<>",MEL!$L:$L,$B12,MEL!$U:$U,"PERM") -> 0 | N12: =SUMIFS(MEL!Y:Y,MEL!Y:Y,"<>",MEL!$L:$L,$B12,MEL!$U:$U,"TEMP")+SUMIFS(MEL!Y:Y,MEL!Y:Y,"<>",MEL!$L:$L,$B12,MEL!$U:$U,"FUT") -> 0 | O12: =M12+N12 -> 0
B13: Total | D13: =SUM(D4:D12) -> 1107.7519 | E13: =SUM(E4:E12) -> 132.22051 | F13: =SUM(F4:F12) -> 1239.9724 | G13: =SUM(G4:G12) -> 1313778.7 | H13: =SUM(H4:H12) -> 128620 | I13: =SUM(I4:I12) -> 1442398.7 | J13: =SUM(J4:J12) -> 1509317.1 | K13: =SUM(K4:K12) -> 147913 | ... O13: =SUM(O4:O12) -> 278133.61
B17: Summary per discipline
B18: Discipline | C18: Description | D18: Footprint PERM (m2) | E18: Footprint FUT/ TEMP (m2) | F18: Footprint total (m2) | G18: Net Dry Weight PERM (kg) | H18: Net Dry Weight FUT/ TEMP (kg) | I18: Net Dry Weight total (kg) | J18: Gross Dry Weight PERM (kg) | K18: Gross Dry Weight FUT/ TEMP (kg) | L18: Gross Dry Weight total (kg) | M18: Content Weight PERM (kg) | N18: Content Weight FUT/ TEMP (kg) | O18: Content Weight total (kg)
B19: A | C19: Project management and administration | D19: =SUMIFS(MEL!R:R,MEL!R:R,"<>",MEL!C:C,B19,MEL!U:U,"PERM") -> 0.32 | E19: =SUMIFS(MEL!R:R,MEL!R:R,"<>",MEL!C:C,B19,MEL!U:U,"FUT")+SUMIFS(MEL!R:R,MEL!R:R,"<>",MEL!C:C,B19,MEL!U:U,"TEMP") -> 0 | F19: =E19+D19 -> 0.32 | G19: =SUMIFS(MEL!W:W,MEL!W:W,"<>",MEL!C:C,B19,MEL!U:U,"PERM") -> 200 | H19: =SUMIFS(MEL!W:W,MEL!W:W,"<>",MEL!C:C,B19,MEL!U:U,"FUT")+SUMIFS(MEL!W:W,MEL!W:W,"<>",MEL!C:C,B19,MEL!U:U,"TEMP") -> 0 | I19: =G19+H19 -> 200 | J19: =SUMIFS(MEL!X:X,MEL!X:X,"<>",MEL!C:C,B19,MEL!U:U,"PERM") -> 230 | K19: =SUMIFS(MEL!X:X,MEL!X:X,"<>",MEL!C:C,B19,MEL!U:U,"FUT")+SUMIFS(MEL!X:X,MEL!X:X,"<>",MEL!C:C,B19,MEL!U:U,"TEMP") -> 0 | L19: =J19+K19 -> 230 | M19: =SUMIFS(MEL!Y:Y,MEL!Y:Y,"<>",MEL!C:C,B19,MEL!U:U,"PERM") -> 0 | N19: =SUMIFS(MEL!Y:Y,MEL!Y:Y,"<>",MEL!C:C,B19,MEL!U:U,"FUT")+SUMIFS(MEL!Y:Y,MEL!Y:Y,"<>",MEL!C:C,B19,MEL!U:U,"TEMP") -> 0 | O19: =M19+N19 -> 0
B20: B | C20: Procurement | D20: =SUMIFS(MEL!R:R,MEL!R:R,"<>",MEL!C:C,B20,MEL!U:U,"PERM") -> 0 | E20: =SUMIFS(MEL!R:R,MEL!R:R,"<>",MEL!C:C,B20,MEL!U:U,"FUT")+SUMIFS(MEL!R:R,MEL!R:R,"<>",MEL!C:C,B20,MEL!U:U,"TEMP") -> 0 | F20: =E20+D20 -> 0 | G20: =SUMIFS(MEL!W:W,MEL!W:W,"<>",MEL!C:C,B20,MEL!U:U,"PERM") -> 0 | H20: =SUMIFS(MEL!W:W,MEL!W:W,"<>",MEL!C:C,B20,MEL!U:U,"FUT")+SUMIFS(MEL!W:W,MEL!W:W,"<>",MEL!C:C,B20,MEL!U:U,"TEMP") -> 0 | I20: =G20+H20 -> 0 | J20: =SUMIFS(MEL!X:X,MEL!X:X,"<>",MEL!C:C,B20,MEL!U:U,"PERM") -> 0 | K20: =SUMIFS(MEL!X:X,MEL!X:X,"<>",MEL!C:C,B20,MEL!U:U,"FUT")+SUMIFS(MEL!X:X,MEL!X:X,"<>",MEL!C:C,B20,MEL!U:U,"TEMP") -> 0 | L20: =J20+K20 -> 0 | M20: =SUMIFS(MEL!Y:Y,MEL!Y:Y,"<>",MEL!C:C,B20,MEL!U:U,"PERM") -> 0 | N20: =SUMIFS(MEL!Y:Y,MEL!Y:Y,"<>",MEL!C:C,B20,MEL!U:U,"FUT")+SUMIFS(MEL!Y:Y,MEL!Y:Y,"<>",MEL!C:C,B20,MEL!U:U,"TEMP") -> 0 | O20: =M20+N20 -> 0
B21: C | C21: Architect and building | D21: =SUMIFS(MEL!R:R,MEL!R:R,"<>",MEL!C:C,B21,MEL!U:U,"PERM") -> 0 | E21: =SUMIFS(MEL!R:R,MEL!R:R,"<>",MEL!C:C,B21,MEL!U:U,"FUT")+SUMIFS(MEL!R:R,MEL!R:R,"<>",MEL!C:C,B21,MEL!U:U,"TEMP") -> 0 | F21: =E21+D21 -> 0 | G21: =SUMIFS(MEL!W:W,MEL!W:W,"<>",MEL!C:C,B21,MEL!U:U,"PERM") -> 0 | H21: =SUMIFS(MEL!W:W,MEL!W:W,"<>",MEL!C:C,B21,MEL!U:U,"FUT")+SUMIFS(MEL!W:W,MEL!W:W,"<>",MEL!C:C,B21,MEL!U:U,"TEMP") -> 0 | I21: =G21+H21 -> 0 | J21: =SUMIFS(MEL!X:X,MEL!X:X,"<>",MEL!C:C,B21,MEL!U:U,"PERM") -> 0 | K21: =SUMIFS(MEL!X:X,MEL!X:X,"<>",MEL!C:C,B21,MEL!U:U,"FUT")+SUMIFS(MEL!X:X,MEL!X:X,"<>",MEL!C:C,B21,MEL!U:U,"TEMP") -> 0 | L21: =J21+K21 -> 0 | M21: =SUMIFS(MEL!Y:Y,MEL!Y:Y,"<>",MEL!C:C,B21,MEL!U:U,"PERM") -> 0 | N21: =SUMIFS(MEL!Y:Y,MEL!Y:Y,"<>",MEL!C:C,B21,MEL!U:U,"FUT")+SUMIFS(MEL!Y:Y,MEL!Y:Y,"<>",MEL!C:C,B21,MEL!U:U,"TEMP") -> 0 | O21: =M21+N21 -> 0
B22: D | C22: Drilling | D22: =SUMIFS(MEL!R:R,MEL!R:R,"<>",MEL!C:C,B22,MEL!U:U,"PERM") -> 0 | E22: =SUMIFS(MEL!R:R,MEL!R:R,"<>",MEL!C:C,B22,MEL!U:U,"FUT")+SUMIFS(MEL!R:R,MEL!R:R,"<>",MEL!C:C,B22,MEL!U:U,"TEMP") -> 0 | F22: =E22+D22 -> 0 | G22: =SUMIFS(MEL!W:W,MEL!W:W,"<>",MEL!C:C,B22,MEL!U:U,"PERM") -> 0 | H22: =SUMIFS(MEL!W:W,MEL!W:W,"<>",MEL!C:C,B22,MEL!U:U,"FUT")+SUMIFS(MEL!W:W,MEL!W:W,"<>",MEL!C:C,B22,MEL!U:U,"TEMP") -> 0 | I22: =G22+H22 -> 0 | J22: =SUMIFS(MEL!X:X,MEL!X:X,"<>",MEL!C:C,B22,MEL!U:U,"PERM") -> 0 | K22: =SUMIFS(MEL!X:X,MEL!X:X,"<>",MEL!C:C,B22,MEL!U:U,"FUT")+SUMIFS(MEL!X:X,MEL!X:X,"<>",MEL!C:C,B22,MEL!U:U,"TEMP") -> 0 | L22: =J22+K22 -> 0 | M22: =SUMIFS(MEL!Y:Y,MEL!Y:Y,"<>",MEL!C:C,B22,MEL!U:U,"PERM") -> 0 | N22: =SUMIFS(MEL!Y:Y,MEL!Y:Y,"<>",MEL!C:C,B22,MEL!U:U,"FUT")+SUMIFS(MEL!Y:Y,MEL!Y:Y,"<>",MEL!C:C,B22,MEL!U:U,"TEMP") -> 0 | O22: =M22+N22 -> 0
B23: E | C23: Electrical | D23: =SUMIFS(MEL!R:R,MEL!R:R,"<>",MEL!C:C,B23,MEL!U:U,"PERM") -> 294.6976 | E23: =SUMIFS(MEL!R:R,MEL!R:R,"<>",MEL!C:C,B23,MEL!U:U,"FUT")+SUMIFS(MEL!R:R,MEL!R:R,"<>",MEL!C:C,B23,MEL!U:U,"TEMP") -> 12.032 | F23: =E23+D23 -> 306.7296 | G23: =SUMIFS(MEL!W:W,MEL!W:W,"<>",MEL!C:C,B23,MEL!U:U,"PERM") -> 338781.74 | H23: =SUMIFS(MEL!W:W,MEL!W:W,"<>",MEL!C:C,B23,MEL!U:U,"FUT")+SUMIFS(MEL!W:W,MEL!W:W,"<>",MEL!C:C,B23,MEL!U:U,"TEMP") -> 9600 | I23: =G23+H23 -> 348381.74 | J23: =SUMIFS(MEL!X:X,MEL!X:X,"<>",MEL!C:C,B23,MEL!U:U,"PERM") -> 389399 | K23: =SUMIFS(MEL!X:X,MEL!X:X,"<>",MEL!C:C,B23,MEL!U:U,"FUT")+SUMIFS(MEL!X:X,MEL!X:X,"<>",MEL!C:C,B23,MEL!U:U,"TEMP") -> 11040 | L23: =J23+K23 -> 400439 | M23: =SUMIFS(MEL!Y:Y,MEL!Y:Y,"<>",MEL!C:C,B23,MEL!U:U,"PERM") -> 43943.61 | N23: =SUMIFS(MEL!Y:Y,MEL!Y:Y,"<>",MEL!C:C,B23,MEL!U:U,"FUT")+SUMIFS(MEL!Y:Y,MEL!Y:Y,"<>",MEL!C:C,B23,MEL!U:U,"TEMP") -> 0 | O23: =M23+N23 -> 43943.61
B24: F | C24: Reservoir | D24: =SUMIFS(MEL!R:R,MEL!R:R,"<>",MEL!C:C,B24,MEL!U:U,"PERM") -> 0 | E24: =SUMIFS(MEL!R:R,MEL!R:R,"<>",MEL!C:C,B24,MEL!U:U,"FUT")+SUMIFS(MEL!R:R,MEL!R:R,"<>",MEL!C:C,B24,MEL!U:U,"TEMP") -> 0 | F24: =E24+D24 -> 0 | G24: =SUMIFS(MEL!W:W,MEL!W:W,"<>",MEL!C:C,B24,MEL!U:U,"PERM") -> 0 | H24: =SUMIFS(MEL!W:W,MEL!W:W,"<>",MEL!C:C,B24,MEL!U:U,"FUT")+SUMIFS(MEL!W:W,MEL!W:W,"<>",MEL!C:C,B24,MEL!U:U,"TEMP") -> 0 | I24: =G24+H24 -> 0 | J24: =SUMIFS(MEL!X:X,MEL!X:X,"<>",MEL!C:C,B24,MEL!U:U,"PERM") -> 0 | K24: =SUMIFS(MEL!X:X,MEL!X:X,"<>",MEL!C:C,B24,MEL!U:U,"FUT")+SUMIFS(MEL!X:X,MEL!X:X,"<>",MEL!C:C,B24,MEL!U:U,"TEMP") -> 0 | L24: =J24+K24 -> 0 | M24: =SUMIFS(MEL!Y:Y,MEL!Y:Y,"<>",MEL!C:C,B24,MEL!U:U,"PERM") -> 0 | N24: =SUMIFS(MEL!Y:Y,MEL!Y:Y,"<>",MEL!C:C,B24,MEL!U:U,"FUT")+SUMIFS(MEL!Y:Y,MEL!Y:Y,"<>",MEL!C:C,B24,MEL!U:U,"TEMP") -> 0 | O24: =M24+N24 -> 0
B25: G | C25: Geosciences | D25: =SUMIFS(MEL!R:R,MEL!R:R,"<>",MEL!C:C,B25,MEL!U:U,"PERM") -> 0 | E25: =SUMIFS(MEL!R:R,MEL!R:R,"<>",MEL!C:C,B25,MEL!U:U,"FUT")+SUMIFS(MEL!R:R,MEL!R:R,"<>",MEL!C:C,B25,MEL!U:U,"TEMP") -> 0 | F25: =E25+D25 -> 0 | G25: =SUMIFS(MEL!W:W,MEL!W:W,"<>",MEL!C:C,B25,MEL!U:U,"PERM") -> 0 | H25: =SUMIFS(MEL!W:W,MEL!W:W,"<>",MEL!C:C,B25,MEL!U:U,"FUT")+SUMIFS(MEL!W:W,MEL!W:W,"<>",MEL!C:C,B25,MEL!U:U,"TEMP") -> 0 | I25: =G25+H25 -> 0 | J25: =SUMIFS(MEL!X:X,MEL!X:X,"<>",MEL!C:C,B25,MEL!U:U,"PERM") -> 0 | K25: =SUMIFS(MEL!X:X,MEL!X:X,"<>",MEL!C:C,B25,MEL!U:U,"FUT")+SUMIFS(MEL!X:X,MEL!X:X,"<>",MEL!C:C,B25,MEL!U:U,"TEMP") -> 0 | L25: =J25+K25 -> 0 | M25: =SUMIFS(MEL!Y:Y,MEL!Y:Y,"<>",MEL!C:C,B25,MEL!U:U,"PERM") -> 0 | N25: =SUMIFS(MEL!Y:Y,MEL!Y:Y,"<>",MEL!C:C,B25,MEL!U:U,"FUT")+SUMIFS(MEL!Y:Y,MEL!Y:Y,"<>",MEL!C:C,B25,MEL!U:U,"TEMP") -> 0 | O25: =M25+N25 -> 0
B26: H | C26: HVAC | D26: =SUMIFS(MEL!R:R,MEL!R:R,"<>",MEL!C:C,B26,MEL!U:U,"PERM") -> 93.1278 | E26: =SUMIFS(MEL!R:R,MEL!R:R,"<>",MEL!C:C,B26,MEL!U:U,"FUT")+SUMIFS(MEL!R:R,MEL!R:R,"<>",MEL!C:C,B26,MEL!U:U,"TEMP") -> 0 | F26: =E26+D26 -> 93.1278 | G26: =SUMIFS(MEL!W:W,MEL!W:W,"<>",MEL!C:C,B26,MEL!U:U,"PERM") -> 47290 | H26: =SUMIFS(MEL!W:W,MEL!W:W,"<>",MEL!C:C,B26,MEL!U:U,"FUT")+SUMIFS(MEL!W:W,MEL!W:W,"<>",MEL!C:C,B26,MEL!U:U,"TEMP") -> 0 | I26: =G26+H26 -> 47290 | J26: =SUMIFS(MEL!X:X,MEL!X:X,"<>",MEL!C:C,B26,MEL!U:U,"PERM") -> 54377.5 | K26: =SUMIFS(MEL!X:X,MEL!X:X,"<>",MEL!C:C,B26,MEL!U:U,"FUT")+SUMIFS(MEL!X:X,MEL!X:X,"<>",MEL!C:C,B26,MEL!U:U,"TEMP") -> 0 | L26: =J26+K26 -> 54377.5 | M26: =SUMIFS(MEL!Y:Y,MEL!Y:Y,"<>",MEL!C:C,B26,MEL!U:U,"PERM") -> 0 | N26: =SUMIFS(MEL!Y:Y,MEL!Y:Y,"<>",MEL!C:C,B26,MEL!U:U,"FUT")+SUMIFS(MEL!Y:Y,MEL!Y:Y,"<>",MEL!C:C,B26,MEL!U:U,"TEMP") -> 0 | O26: =M26+N26 -> 0
B27: J | C27: Automation | D27: =SUMIFS(MEL!R:R,MEL!R:R,"<>",MEL!C:C,B27,MEL!U:U,"PERM") -> 84.13 | E27: =SUMIFS(MEL!R:R,MEL!R:R,"<>",MEL!C:C,B27,MEL!U:U,"FUT")+SUMIFS(MEL!R:R,MEL!R:R,"<>",MEL!C:C,B27,MEL!U:U,"TEMP") -> 4.48 | F27: =E27+D27 -> 88.61 | G27: =SUMIFS(MEL!W:W,MEL!W:W,"<>",MEL!C:C,B27,MEL!U:U,"PERM") -> 37660 | H27: =SUMIFS(MEL!W:W,MEL!W:W,"<>",MEL!C:C,B27,MEL!U:U,"FUT")+SUMIFS(MEL!W:W,MEL!W:W,"<>",MEL!C:C,B27,MEL!U:U,"TEMP") -> 2000 | I27: =G27+H27 -> 39660 | J27: =SUMIFS(MEL!X:X,MEL!X:X,"<>",MEL!C:C,B27,MEL!U:U,"PERM") -> 43309 | K27: =SUMIFS(MEL!X:X,MEL!X:X,"<>",MEL!C:C,B27,MEL!U:U,"FUT")+SUMIFS(MEL!X:X,MEL!X:X,"<>",MEL!C:C,B27,MEL!U:U,"TEMP") -> 2300 | L27: =J27+K27 -> 45609 | M27: =SUMIFS(MEL!Y:Y,MEL!Y:Y,"<>",MEL!C:C,B27,MEL!U:U,"PERM") -> 4000 | N27: =SUMIFS(MEL!Y:Y,MEL!Y:Y,"<>",MEL!C:C,B27,MEL!U:U,"FUT")+SUMIFS(MEL!Y:Y,MEL!Y:Y,"<>",MEL!C:C,B27,MEL!U:U,"TEMP") -> 0 | O27: =M27+N27 -> 4000
B28: K | C28: Not in use | D28: =SUMIFS(MEL!R:R,MEL!R:R,"<>",MEL!C:C,B28,MEL!U:U,"PERM") -> 0 | E28: =SUMIFS(MEL!R:R,MEL!R:R,"<>",MEL!C:C,B28,MEL!U:U,"FUT")+SUMIFS(MEL!R:R,MEL!R:R,"<>",MEL!C:C,B28,MEL!U:U,"TEMP") -> 0 | F28: =E28+D28 -> 0 | G28: =SUMIFS(MEL!W:W,MEL!W:W,"<>",MEL!C:C,B28,MEL!U:U,"PERM") -> 0 | H28: =SUMIFS(MEL!W:W,MEL!W:W,"<>",MEL!C:C,B28,MEL!U:U,"FUT")+SUMIFS(MEL!W:W,MEL!W:W,"<>",MEL!C:C,B28,MEL!U:U,"TEMP") -> 0 | I28: =G28+H28 -> 0 | J28: =SUMIFS(MEL!X:X,MEL!X:X,"<>",MEL!C:C,B28,MEL!U:U,"PERM") -> 0 | K28: =SUMIFS(MEL!X:X,MEL!X:X,"<>",MEL!C:C,B28,MEL!U:U,"FUT")+SUMIFS(MEL!X:X,MEL!X:X,"<>",MEL!C:C,B28,MEL!U:U,"TEMP") -> 0 | L28: =J28+K28 -> 0 | M28: =SUMIFS(MEL!Y:Y,MEL!Y:Y,"<>",MEL!C:C,B28,MEL!U:U,"PERM") -> 0 | N28: =SUMIFS(MEL!Y:Y,MEL!Y:Y,"<>",MEL!C:C,B28,MEL!U:U,"FUT")+SUMIFS(MEL!Y:Y,MEL!Y:Y,"<>",MEL!C:C,B28,MEL!U:U,"TEMP") -> 0 | O28: =M28+N28 -> 0
B29: L | C29: Piping and Layout | D29: =SUMIFS(MEL!R:R,MEL!R:R,"<>",MEL!C:C,B29,MEL!U:U,"PERM") -> 0 | E29: =SUMIFS(MEL!R:R,MEL!R:R,"<>",MEL!C:C,B29,MEL!U:U,"FUT")+SUMIFS(MEL!R:R,MEL!R:R,"<>",MEL!C:C,B29,MEL!U:U,"TEMP") -> 0 | F29: =E29+D29 -> 0 | G29: =SUMIFS(MEL!W:W,MEL!W:W,"<>",MEL!C:C,B29,MEL!U:U,"PERM") -> 0 | H29: =SUMIFS(MEL!W:W,MEL!W:W,"<>",MEL!C:C,B29,MEL!U:U,"FUT")+SUMIFS(MEL!W:W,MEL!W:W,"<>",MEL!C:C,B29,MEL!U:U,"TEMP") -> 0 | I29: =G29+H29 -> 0 | J29: =SUMIFS(MEL!X:X,MEL!X:X,"<>",MEL!C:C,B29,MEL!U:U,"PERM") -> 0 | K29: =SUMIFS(MEL!X:X,MEL!X:X,"<>",MEL!C:C,B29,MEL!U:U,"FUT")+SUMIFS(MEL!X:X,MEL!X:X,"<>",MEL!C:C,B29,MEL!U:U,"TEMP") -> 0 | L29: =J29+K29 -> 0 | M29: =SUMIFS(MEL!Y:Y,MEL!Y:Y,"<>",MEL!C:C,B29,MEL!U:U,"PERM") -> 0 | N29: =SUMIFS(MEL!Y:Y,MEL!Y:Y,"<>",MEL!C:C,B29,MEL!U:U,"FUT")+SUMIFS(MEL!Y:Y,MEL!Y:Y,"<>",MEL!C:C,B29,MEL!U:U,"TEMP") -> 0 | O29: =M29+N29 -> 0
B30: M | C30: Material Technology | D30: =SUMIFS(MEL!R:R,MEL!R:R,"<>",MEL!C:C,B30,MEL!U:U,"PERM") -> 0 | E30: =SUMIFS(MEL!R:R,MEL!R:R,"<>",MEL!C:C,B30,MEL!U:U,"FUT")+SUMIFS(MEL!R:R,MEL!R:R,"<>",MEL!C:C,B30,MEL!U:U,"TEMP") -> 0 | F30: =E30+D30 -> 0 | G30: =SUMIFS(MEL!W:W,MEL!W:W,"<>",MEL!C:C,B30,MEL!U:U,"PERM") -> 0 | H30: =SUMIFS(MEL!W:W,MEL!W:W,"<>",MEL!C:C,B30,MEL!U:U,"FUT")+SUMIFS(MEL!W:W,MEL!W:W,"<>",MEL!C:C,B30,MEL!U:U,"TEMP") -> 0 | I30: =G30+H30 -> 0 | J30: =SUMIFS(MEL!X:X,MEL!X:X,"<>",MEL!C:C,B30,MEL!U:U,"PERM") -> 0 | K30: =SUMIFS(MEL!X:X,MEL!X:X,"<>",MEL!C:C,B30,MEL!U:U,"FUT")+SUMIFS(MEL!X:X,MEL!X:X,"<>",MEL!C:C,B30,MEL!U:U,"TEMP") -> 0 | L30: =J30+K30 -> 0 | M30: =SUMIFS(MEL!Y:Y,MEL!Y:Y,"<>",MEL!C:C,B30,MEL!U:U,"PERM") -> 0 | N30: =SUMIFS(MEL!Y:Y,MEL!Y:Y,"<>",MEL!C:C,B30,MEL!U:U,"FUT")+SUMIFS(MEL!Y:Y,MEL!Y:Y,"<>",MEL!C:C,B30,MEL!U:U,"TEMP") -> 0 | O30: =M30+N30 -> 0
... B42: Z | C42: Multidiscipline | D42: =SUMIFS(MEL!R:R,MEL!R:R,"<>",MEL!C:C,B42,MEL!U:U,"PERM") -> 0 | E42: =SUMIFS(MEL!R:R,MEL!R:R,"<>",MEL!C:C,B42,MEL!U:U,"FUT")+SUMIFS(MEL!R:R,MEL!R:R,"<>",MEL!C:C,B42,MEL!U:U,"TEMP") -> 0 | F42: =E42+D42 -> 0 | G42: =SUMIFS(MEL!W:W,MEL!W:W,"<>",MEL!C:C,B42,MEL!U:U,"PERM") -> 0 | H42: =SUMIFS(MEL!W:W,MEL!W:W,"<>",MEL!C:C,B42,MEL!U:U,"FUT")+SUMIFS(MEL!W:W,MEL!W:W,"<>",MEL!C:C,B42,MEL!U:U,"TEMP") -> 0 | I42: =G42+H42 -> 0 | J42: =SUMIFS(MEL!X:X,MEL!X:X,"<>",MEL!C:C,B42,MEL!U:U,"PERM") -> 0 | K42: =SUMIFS(MEL!X:X,MEL!X:X,"<>",MEL!C:C,B42,MEL!U:U,"FUT")+SUMIFS(MEL!X:X,MEL!X:X,"<>",MEL!C:C,B42,MEL!U:U,"TEMP") -> 0 | L42: =J42+K42 -> 0 | M42: =SUMIFS(MEL!Y:Y,MEL!Y:Y,"<>",MEL!C:C,B42,MEL!U:U,"PERM") -> 0 | N42: =SUMIFS(MEL!Y:Y,MEL!Y:Y,"<>",MEL!C:C,B42,MEL!U:U,"FUT")+SUMIFS(MEL!Y:Y,MEL!Y:Y,"<>",MEL!C:C,B42,MEL!U:U,"TEMP") -> 0 | O42: =M42+N42 -> 0
B43: Total | D43: =SUM(D19:D42) -> 1107.7519 | E43: =SUM(E19:E42) -> 132.22051 | F43: =SUM(F19:F42) -> 1239.9724 | G43: =SUM(G19:G42) -> 1313778.7 | H43: =SUM(H19:H42) -> 128620 | I43: =SUM(I19:I42) -> 1442398.7 | J43: =SUM(J19:J42) -> 1509317 | K43: =SUM(K19:K42) -> 147913 | ... O43: =SUM(O19:O42) -> 278133.61
B47: Summary per system group
B48: System no. | C48: Description | D48: Footprint PERM (m2) | E48: Footprint FUT/ TEMP (m2) | F48: Footprint total (m2) | G48: Net Dry Weight PERM (kg) | H48: Net Dry Weight FUT/ TEMP (kg) | I48: Net Dry Weight total (kg) | J48: Gross Dry Weight PERM (kg) | K48: Gross Dry Weight FUT/ TEMP (kg) | L48: Gross Dry Weight total (kg) | M48: Content Weight PERM (kg) | N48: Content Weight FUT/ TEMP (kg) | O48: Content Weight total (kg)
B49: 00 – 09 | C49: Project/facility specific systems | D49: =SUMIFS(MEL!R:R,MEL!R:R,"<>",MEL!$I:$I,">=0",MEL!$I:$I,"<=9",MEL!$U:$U,"PERM") -> 0 | E49: =SUMIFS(MEL!R:R,MEL!R:R,"<>",MEL!$I:$I,">=0",MEL!$I:$I,"<=9",MEL!$U:$U,"FUT")+SUMIFS(MEL!R:R,MEL!R:R,"<>",MEL!$I:$I,">=0",MEL!$I:$I,"<=9",MEL!$U:$U,"TEMP") -> 0 | F49: =D49+E49 -> 0 | G49: =SUMIFS(MEL!W:W,MEL!W:W,"<>",MEL!$I:$I,">=0",MEL!$I:$I,"<=9",MEL!$U:$U,"PERM") -> 0 | H49: =SUMIFS(MEL!W:W,MEL!W:W,"<>",MEL!$I:$I,">=0",MEL!$I:$I,"<=9",MEL!$U:$U,"FUT")+SUMIFS(MEL!W:W,MEL!W:W,"<>",MEL!$I:$I,">=0",MEL!$I:$I,"<=9",MEL!$U:$U,"TEMP") -> 0 | I49: =G49+H49 -> 0 | J49: =SUMIFS(MEL!X:X,MEL!X:X,"<>",MEL!$I:$I,">=0",MEL!$I:$I,"<=9",MEL!$U:$U,"PERM") -> 0 | K49: =SUMIFS(MEL!X:X,MEL!X:X,"<>",MEL!$I:$I,">=0",MEL!$I:$I,"<=9",MEL!$U:$U,"FUT")+SUMIFS(MEL!X:X,MEL!X:X,"<>",MEL!$I:$I,">=0",MEL!$I:$I,"<=9",MEL!$U:$U,"TEMP") -> 0 | L49: =J49+K49 -> 0 | M49: =SUMIFS(MEL!Y:Y,MEL!Y:Y,"<>",MEL!$I:$I,">=0",MEL!$I:$I,"<=9",MEL!$U:$U,"PERM") -> 0 | N49: =SUMIFS(MEL!Y:Y,MEL!Y:Y,"<>",MEL!$I:$I,">=0",MEL!$I:$I,"<=9",MEL!$U:$U,"FUT")+SUMIFS(MEL!Y:Y,MEL!Y:Y,"<>",MEL!$I:$I,">=0",MEL!$I:$I,"<=9",MEL!$U:$U,"TEMP") -> 0 | O49: =M49+N49 -> 0
B50: 10 – 19 | C50: Drilling, well and Subsea Production System (SPS) | D50: =SUMIFS(MEL!R:R,MEL!R:R,"<>",MEL!$I:$I,">=10",MEL!$I:$I,"<=19",MEL!$U:$U,"PERM") -> 48.3 | E50: =SUMIFS(MEL!R:R,MEL!R:R,"<>",MEL!$I:$I,">=10",MEL!$I:$I,"<=19",MEL!$U:$U,"FUT")+SUMIFS(MEL!R:R,MEL!R:R,"<>",MEL!$I:$I,">=10",MEL!$I:$I,"<=19",MEL!$U:$U,"TEMP") -> 4.72 | F50: =D50+E50 -> 53.02 | G50: =SUMIFS(MEL!W:W,MEL!W:W,"<>",MEL!$I:$I,">=10",MEL!$I:$I,"<=19",MEL!$U:$U,"PERM") -> 38300 | H50: =SUMIFS(MEL!W:W,MEL!W:W,"<>",MEL!$I:$I,">=10",MEL!$I:$I,"<=19",MEL!$U:$U,"FUT")+SUMIFS(MEL!W:W,MEL!W:W,"<>",MEL!$I:$I,">=10",MEL!$I:$I,"<=19",MEL!$U:$U,"TEMP") -> 13540 | I50: =G50+H50 -> 51840 | J50: =SUMIFS(MEL!X:X,MEL!X:X,"<>",MEL!$I:$I,">=10",MEL!$I:$I,"<=19",MEL!$U:$U,"PERM") -> 43845 | K50: =SUMIFS(MEL!X:X,MEL!X:X,"<>",MEL!$I:$I,">=10",MEL!$I:$I,"<=19",MEL!$U:$U,"FUT")+SUMIFS(MEL!X:X,MEL!X:X,"<>",MEL!$I:$I,">=10",MEL!$I:$I,"<=19",MEL!$U:$U,"TEMP") -> 15571 | L50: =J50+K50 -> 59416 | M50: =SUMIFS(MEL!Y:Y,MEL!Y:Y,"<>",MEL!$I:$I,">=10",MEL!$I:$I,"<=19",MEL!$U:$U,"PERM") -> 4000 | N50: =SUMIFS(MEL!Y:Y,MEL!Y:Y,"<>",MEL!$I:$I,">=10",MEL!$I:$I,"<=19",MEL!$U:$U,"FUT")+SUMIFS(MEL!Y:Y,MEL!Y:Y,"<>",MEL!$I:$I,">=10",MEL!$I:$I,"<=19",MEL!$U:$U,"TEMP") -> 0 | O50: =M50+N50 -> 4000
B51: 20 – 29 | C51: Main process systems | D51: =SUMIFS(MEL!R:R,MEL!R:R,"<>",MEL!$I:$I,">=20",MEL!$I:$I,"<=29",MEL!$U:$U,"PERM") -> 393.83875 | E51: =SUMIFS(MEL!R:R,MEL!R:R,"<>",MEL!$I:$I,">=20",MEL!$I:$I,"<=29",MEL!$U:$U,"FUT")+SUMIFS(MEL!R:R,MEL!R:R,"<>",MEL!$I:$I,">=20",MEL!$I:$I,"<=29",MEL!$U:$U,"TEMP") -> 12.08 | F51: =D51+E51 -> 405.91875 | G51: =SUMIFS(MEL!W:W,MEL!W:W,"<>",MEL!$I:$I,">=20",MEL!$I:$I,"<=29",MEL!$U:$U,"PERM") -> 726944 | H51: =SUMIFS(MEL!W:W,MEL!W:W,"<>",MEL!$I:$I,">=20",MEL!$I:$I,"<=29",MEL!$U:$U,"FUT")+SUMIFS(MEL!W:W,MEL!W:W,"<>",MEL!$I:$I,">=20",MEL!$I:$I,"<=29",MEL!$U:$U,"TEMP") -> 21270 | I51: =G51+H51 -> 748214 | J51: =SUMIFS(MEL!X:X,MEL!X:X,"<>",MEL!$I:$I,">=20",MEL!$I:$I,"<=29",MEL!$U:$U,"PERM") -> 835985.6 | K51: =SUMIFS(MEL!X:X,MEL!X:X,"<>",MEL!$I:$I,">=20",MEL!$I:$I,"<=29",MEL!$U:$U,"FUT")+SUMIFS(MEL!X:X,MEL!X:X,"<>",MEL!$I:$I,">=20",MEL!$I:$I,"<=29",MEL!$U:$U,"TEMP") -> 24460.5 | L51: =J51+K51 -> 860446.1 | M51: =SUMIFS(MEL!Y:Y,MEL!Y:Y,"<>",MEL!$I:$I,">=20",MEL!$I:$I,"<=29",MEL!$U:$U,"PERM") -> 168590 | N51: =SUMIFS(MEL!Y:Y,MEL!Y:Y,"<>",MEL!$I:$I,">=20",MEL!$I:$I,"<=29",MEL!$U:$U,"FUT")+SUMIFS(MEL!Y:Y,MEL!Y:Y,"<>",MEL!$I:$I,">=20",MEL!$I:$I,"<=29",MEL!$U:$U,"TEMP") -> 0 | O51: =M51+N51 -> 168590
B52: 30 – 39 | C52: Export and by-product handling systems | D52: =SUMIFS(MEL!R:R,MEL!R:R,"<>",MEL!$I:$I,">=30",MEL!$I:$I,"<=39",MEL!$U:$U,"PERM") -> 0 | E52: =SUMIFS(MEL!R:R,MEL!R:R,"<>",MEL!$I:$I,">=30",MEL!$I:$I,"<=39",MEL!$U:$U,"FUT")+SUMIFS(MEL!R:R,MEL!R:R,"<>",MEL!$I:$I,">=30",MEL!$I:$I,"<=39",MEL!$U:$U,"TEMP") -> 0 | F52: =D52+E52 -> 0 | G52: =SUMIFS(MEL!W:W,MEL!W:W,"<>",MEL!$I:$I,">=30",MEL!$I:$I,"<=39",MEL!$U:$U,"PERM") -> 0 | H52: =SUMIFS(MEL!W:W,MEL!W:W,"<>",MEL!$I:$I,">=30",MEL!$I:$I,"<=39",MEL!$U:$U,"FUT")+SUMIFS(MEL!W:W,MEL!W:W,"<>",MEL!$I:$I,">=30",MEL!$I:$I,"<=39",MEL!$U:$U,"TEMP") -> 0 | I52: =G52+H52 -> 0 | J52: =SUMIFS(MEL!X:X,MEL!X:X,"<>",MEL!$I:$I,">=30",MEL!$I:$I,"<=39",MEL!$U:$U,"PERM") -> 0 | K52: =SUMIFS(MEL!X:X,MEL!X:X,"<>",MEL!$I:$I,">=30",MEL!$I:$I,"<=39",MEL!$U:$U,"FUT")+SUMIFS(MEL!X:X,MEL!X:X,"<>",MEL!$I:$I,">=30",MEL!$I:$I,"<=39",MEL!$U:$U,"TEMP") -> 0 | L52: =J52+K52 -> 0 | M52: =SUMIFS(MEL!Y:Y,MEL!Y:Y,"<>",MEL!$I:$I,">=30",MEL!$I:$I,"<=39",MEL!$U:$U,"PERM") -> 0 | N52: =SUMIFS(MEL!Y:Y,MEL!Y:Y,"<>",MEL!$I:$I,">=30",MEL!$I:$I,"<=39",MEL!$U:$U,"FUT")+SUMIFS(MEL!Y:Y,MEL!Y:Y,"<>",MEL!$I:$I,">=30",MEL!$I:$I,"<=39",MEL!$U:$U,"TEMP") -> 0 | O52: =M52+N52 -> 0
B53: 40 – 69 | C53: Process support and utility systems | D53: =SUMIFS(MEL!R:R,MEL!R:R,"<>",MEL!$I:$I,">=40",MEL!$I:$I,"<=69",MEL!$U:$U,"PERM") -> 119.47774 | E53: =SUMIFS(MEL!R:R,MEL!R:R,"<>",MEL!$I:$I,">=40",MEL!$I:$I,"<=69",MEL!$U:$U,"FUT")+SUMIFS(MEL!R:R,MEL!R:R,"<>",MEL!$I:$I,">=40",MEL!$I:$I,"<=69",MEL!$U:$U,"TEMP") -> 80.762944 | F53: =D53+E53 -> 200.24069 | G53: =SUMIFS(MEL!W:W,MEL!W:W,"<>",MEL!$I:$I,">=40",MEL!$I:$I,"<=69",MEL!$U:$U,"PERM") -> 116203 | H53: =SUMIFS(MEL!W:W,MEL!W:W,"<>",MEL!$I:$I,">=40",MEL!$I:$I,"<=69",MEL!$U:$U,"FUT")+SUMIFS(MEL!W:W,MEL!W:W,"<>",MEL!$I:$I,">=40",MEL!$I:$I,"<=69",MEL!$U:$U,"TEMP") -> 71940 | I53: =G53+H53 -> 188143 | J53: =SUMIFS(MEL!X:X,MEL!X:X,"<>",MEL!$I:$I,">=40",MEL!$I:$I,"<=69",MEL!$U:$U,"PERM") -> 132310.95 | K53: =SUMIFS(MEL!X:X,MEL!X:X,"<>",MEL!$I:$I,">=40",MEL!$I:$I,"<=69",MEL!$U:$U,"FUT")+SUMIFS(MEL!X:X,MEL!X:X,"<>",MEL!$I:$I,">=40",MEL!$I:$I,"<=69",MEL!$U:$U,"TEMP") -> 82731 | L53: =J53+K53 -> 215041.95 | M53: =SUMIFS(MEL!Y:Y,MEL!Y:Y,"<>",MEL!$I:$I,">=40",MEL!$I:$I,"<=69",MEL!$U:$U,"PERM") -> 85600 | N53: =SUMIFS(MEL!Y:Y,MEL!Y:Y,"<>",MEL!$I:$I,">=40",MEL!$I:$I,"<=69",MEL!$U:$U,"FUT")+SUMIFS(MEL!Y:Y,MEL!Y:Y,"<>",MEL!$I:$I,">=40",MEL!$I:$I,"<=69",MEL!$U:$U,"TEMP") -> 0 | O53: =M53+N53 -> 85600
B54: 70 – 79 | C54: Safety systems | D54: =SUMIFS(MEL!R:R,MEL!R:R,"<>",MEL!$I:$I,">=70",MEL!$I:$I,"<=79",MEL!$U:$U,"PERM") -> 319.1816 | E54: =SUMIFS(MEL!R:R,MEL!R:R,"<>",MEL!$I:$I,">=70",MEL!$I:$I,"<=79",MEL!$U:$U,"FUT")+SUMIFS(MEL!R:R,MEL!R:R,"<>",MEL!$I:$I,">=70",MEL!$I:$I,"<=79",MEL!$U:$U,"TEMP") -> 30.177564 | F54: =D54+E54 -> 349.35916 | G54: =SUMIFS(MEL!W:W,MEL!W:W,"<>",MEL!$I:$I,">=70",MEL!$I:$I,"<=79",MEL!$U:$U,"PERM") -> 219430 | H54: =SUMIFS(MEL!W:W,MEL!W:W,"<>",MEL!$I:$I,">=70",MEL!$I:$I,"<=79",MEL!$U:$U,"FUT")+SUMIFS(MEL!W:W,MEL!W:W,"<>",MEL!$I:$I,">=70",MEL!$I:$I,"<=79",MEL!$U:$U,"TEMP") -> 19870 | I54: =G54+H54 -> 239300 | J54: =SUMIFS(MEL!X:X,MEL!X:X,"<>",MEL!$I:$I,">=70",MEL!$I:$I,"<=79",MEL!$U:$U,"PERM") -> 252338.5 | K54: =SUMIFS(MEL!X:X,MEL!X:X,"<>",MEL!$I:$I,">=70",MEL!$I:$I,"<=79",MEL!$U:$U,"FUT")+SUMIFS(MEL!X:X,MEL!X:X,"<>",MEL!$I:$I,">=70",MEL!$I:$I,"<=79",MEL!$U:$U,"TEMP") -> 22850.5 | L54: =J54+K54 -> 275189 | M54: =SUMIFS(MEL!Y:Y,MEL!Y:Y,"<>",MEL!$I:$I,">=70",MEL!$I:$I,"<=79",MEL!$U:$U,"PERM") -> 0 | N54: =SUMIFS(MEL!Y:Y,MEL!Y:Y,"<>",MEL!$I:$I,">=70",MEL!$I:$I,"<=79",MEL!$U:$U,"FUT")+SUMIFS(MEL!Y:Y,MEL!Y:Y,"<>",MEL!$I:$I,">=70",MEL!$I:$I,"<=79",MEL!$U:$U,"TEMP") -> 0 | O54: =M54+N54 -> 0
B55: 80 – 85 | C55: Electrical power generation and distribution systems | D55: =SUMIFS(MEL!R:R,MEL!R:R,"<>",MEL!$I:$I,">=80",MEL!$I:$I,"<=85",MEL!$U:$U,"PERM") -> 160.2338 | E55: =SUMIFS(MEL!R:R,MEL!R:R,"<>",MEL!$I:$I,">=80",MEL!$I:$I,"<=85",MEL!$U:$U,"FUT")+SUMIFS(MEL!R:R,MEL!R:R,"<>",MEL!$I:$I,">=80",MEL!$I:$I,"<=85",MEL!$U:$U,"TEMP") -> 0 | F55: =D55+E55 -> 160.2338 | G55: =SUMIFS(MEL!W:W,MEL!W:W,"<>",MEL!$I:$I,">=80",MEL!$I:$I,"<=85",MEL!$U:$U,"PERM") -> 187241.74 | H55: =SUMIFS(MEL!W:W,MEL!W:W,"<>",MEL!$I:$I,">=80",MEL!$I:$I,"<=85",MEL!$U:$U,"FUT")+SUMIFS(MEL!W:W,MEL!W:W,"<>",MEL!$I:$I,">=80",MEL!$I:$I,"<=85",MEL!$U:$U,"TEMP") -> 0 | I55: =G55+H55 -> 187241.74 | J55: =SUMIFS(MEL!X:X,MEL!X:X,"<>",MEL!$I:$I,">=80",MEL!$I:$I,"<=85",MEL!$U:$U,"PERM") -> 215328 | K55: =SUMIFS(MEL!X:X,MEL!X:X,"<>",MEL!$I:$I,">=80",MEL!$I:$I,"<=85",MEL!$U:$U,"FUT")+SUMIFS(MEL!X:X,MEL!X:X,"<>",MEL!$I:$I,">=80",MEL!$I:$I,"<=85",MEL!$U:$U,"TEMP") -> 0 | L55: =J55+K55 -> 215328 | M55: =SUMIFS(MEL!Y:Y,MEL!Y:Y,"<>",MEL!$I:$I,">=80",MEL!$I:$I,"<=85",MEL!$U:$U,"PERM") -> 19943.61 | N55: =SUMIFS(MEL!Y:Y,MEL!Y:Y,"<>",MEL!$I:$I,">=80",MEL!$I:$I,"<=85",MEL!$U:$U,"FUT")+SUMIFS(MEL!Y:Y,MEL!Y:Y,"<>",MEL!$I:$I,">=80",MEL!$I:$I,"<=85",MEL!$U:$U,"TEMP") -> 0 | O55: =M55+N55 -> 19943.61
B56: 86 – 89 | C56: Automation and Telecommunication systems | D56: =SUMIFS(MEL!R:R,MEL!R:R,"<>",MEL!$I:$I,">=86",MEL!$I:$I,"<=89",MEL!$U:$U,"PERM") -> 66.72 | E56: =SUMIFS(MEL!R:R,MEL!R:R,"<>",MEL!$I:$I,">=86",MEL!$I:$I,"<=89",MEL!$U:$U,"FUT")+SUMIFS(MEL!R:R,MEL!R:R,"<>",MEL!$I:$I,">=86",MEL!$I:$I,"<=89",MEL!$U:$U,"TEMP") -> 4.48 | F56: =D56+E56 -> 71.2 | G56: =SUMIFS(MEL!W:W,MEL!W:W,"<>",MEL!$I:$I,">=86",MEL!$I:$I,"<=89",MEL!$U:$U,"PERM") -> 25660 | H56: =SUMIFS(MEL!W:W,MEL!W:W,"<>",MEL!$I:$I,">=86",MEL!$I:$I,"<=89",MEL!$U:$U,"FUT")+SUMIFS(MEL!W:W,MEL!W:W,"<>",MEL!$I:$I,">=86",MEL!$I:$I,"<=89",MEL!$U:$U,"TEMP") -> 2000 | I56: =G56+H56 -> 27660 | J56: =SUMIFS(MEL!X:X,MEL!X:X,"<>",MEL!$I:$I,">=86",MEL!$I:$I,"<=89",MEL!$U:$U,"PERM") -> 29509 | K56: =SUMIFS(MEL!X:X,MEL!X:X,"<>",MEL!$I:$I,">=86",MEL!$I:$I,"<=89",MEL!$U:$U,"FUT")+SUMIFS(MEL!X:X,MEL!X:X,"<>",MEL!$I:$I,">=86",MEL!$I:$I,"<=89",MEL!$U:$U,"TEMP") -> 2300 | L56: =J56+K56 -> 31809 | M56: =SUMIFS(MEL!Y:Y,MEL!Y:Y,"<>",MEL!$I:$I,">=86",MEL!$I:$I,"<=89",MEL!$U:$U,"PERM") -> 0 | N56: =SUMIFS(MEL!Y:Y,MEL!Y:Y,"<>",MEL!$I:$I,">=86",MEL!$I:$I,"<=89",MEL!$U:$U,"FUT")+SUMIFS(MEL!Y:Y,MEL!Y:Y,"<>",MEL!$I:$I,">=86",MEL!$I:$I,"<=89",MEL!$U:$U,"TEMP") -> 0 | O56: =M56+N56 -> 0
B57: 90 – 99 | C57: Structural, Civil, Marine and Architectural systems | D57: =SUMIFS(MEL!R:R,MEL!R:R,"<>",MEL!$I:$I,">=90",MEL!$I:$I,"<=99",MEL!$U:$U,"PERM") -> 0 | E57: =SUMIFS(MEL!R:R,MEL!R:R,"<>",MEL!$I:$I,">=90",MEL!$I:$I,"<=99",MEL!$U:$U,"FUT")+SUMIFS(MEL!R:R,MEL!R:R,"<>",MEL!$I:$I,">=90",MEL!$I:$I,"<=99",MEL!$U:$U,"TEMP") -> 0 | F57: =D57+E57 -> 0 | G57: =SUMIFS(MEL!W:W,MEL!W:W,"<>",MEL!$I:$I,">=90",MEL!$I:$I,"<=99",MEL!$U:$U,"PERM") -> 0 | H57: =SUMIFS(MEL!W:W,MEL!W:W,"<>",MEL!$I:$I,">=90",MEL!$I:$I,"<=99",MEL!$U:$U,"FUT")+SUMIFS(MEL!W:W,MEL!W:W,"<>",MEL!$I:$I,">=90",MEL!$I:$I,"<=99",MEL!$U:$U,"TEMP") -> 0 | I57: =G57+H57 -> 0 | J57: =SUMIFS(MEL!X:X,MEL!X:X,"<>",MEL!$I:$I,">=90",MEL!$I:$I,"<=99",MEL!$U:$U,"PERM") -> 0 | K57: =SUMIFS(MEL!X:X,MEL!X:X,"<>",MEL!$I:$I,">=90",MEL!$I:$I,"<=99",MEL!$U:$U,"FUT")+SUMIFS(MEL!X:X,MEL!X:X,"<>",MEL!$I:$I,">=90",MEL!$I:$I,"<=99",MEL!$U:$U,"TEMP") -> 0 | L57: =J57+K57 -> 0 | M57: =SUMIFS(MEL!Y:Y,MEL!Y:Y,"<>",MEL!$I:$I,">=90",MEL!$I:$I,"<=99",MEL!$U:$U,"PERM") -> 0 | N57: =SUMIFS(MEL!Y:Y,MEL!Y:Y,"<>",MEL!$I:$I,">=90",MEL!$I:$I,"<=99",MEL!$U:$U,"FUT")+SUMIFS(MEL!Y:Y,MEL!Y:Y,"<>",MEL!$I:$I,">=90",MEL!$I:$I,"<=99",MEL!$U:$U,"TEMP") -> 0 | O57: =M57+N57 -> 0
B58: Total | D58: =SUM(D49:D57) -> 1107.7519 | E58: =SUM(E49:E57) -> 132.22051 | F58: =SUM(F49:F57) -> 1239.9724 | G58: =SUM(G49:G57) -> 1313778.7 | H58: =SUM(H49:H57) -> 128620 | I58: =SUM(I49:I57) -> 1442398.7 | J58: =SUM(J49:J57) -> 1509317 | K58: =SUM(K49:K57) -> 147913 | ... O58: =SUM(O49:O57) -> 278133.61
B62: Summary per individual system
B63: System no. | C63: Description | D63: Footprint PERM (m2) | E63: Footprint FUT/ TEMP (m2) | F63: Footprint total (m2) | G63: Net Dry Weight PERM (kg) | H63: Net Dry Weight FUT/ TEMP (kg) | I63: Net Dry Weight total (kg) | J63: Gross Dry Weight PERM (kg) | K63: Gross Dry Weight FUT/ TEMP (kg) | L63: Gross Dry Weight total (kg) | M63: Content Weight PERM (kg) | N63: Content Weight FUT/ TEMP (kg) | O63: Content Weight total (kg)
B64: 00 – 09 | C64: Project/facility specific systems | D64: =SUMIFS(MEL!R:R,MEL!R:R,"<>",MEL!$I:$I,">=0",MEL!$I:$I,"<=9",MEL!$U:$U,"PERM") -> 0 | E64: =SUMIFS(MEL!R:R,MEL!R:R,"<>",MEL!$I:$I,">=0",MEL!$I:$I,"<=9",MEL!$U:$U,"FUT")+SUMIFS(MEL!R:R,MEL!R:R,"<>",MEL!$I:$I,">=0",MEL!$I:$I,"<=9",MEL!$U:$U,"TEMP") -> 0 | F64: =D64+E64 -> 0 | G64: =SUMIFS(MEL!W:W,MEL!W:W,"<>",MEL!$I:$I,">=0",MEL!$I:$I,"<=9",MEL!$U:$U,"PERM") -> 0 | H64: =SUMIFS(MEL!W:W,MEL!W:W,"<>",MEL!$I:$I,">=0",MEL!$I:$I,"<=9",MEL!$U:$U,"FUT")+SUMIFS(MEL!W:W,MEL!W:W,"<>",MEL!$I:$I,">=0",MEL!$I:$I,"<=9",MEL!$U:$U,"TEMP") -> 0 | I64: =G64+H64 -> 0 | J64: =SUMIFS(MEL!X:X,MEL!X:X,"<>",MEL!$I:$I,">=0",MEL!$I:$I,"<=9",MEL!$U:$U,"PERM") -> 0 | K64: =SUMIFS(MEL!X:X,MEL!X:X,"<>",MEL!$I:$I,">=0",MEL!$I:$I,"<=9",MEL!$U:$U,"FUT")+SUMIFS(MEL!X:X,MEL!X:X,"<>",MEL!$I:$I,">=0",MEL!$I:$I,"<=9",MEL!$U:$U,"TEMP") -> 0 | L64: =J64+K64 -> 0 | M64: =SUMIFS(MEL!Y:Y,MEL!Y:Y,"<>",MEL!$I:$I,">=0",MEL!$I:$I,"<=9",MEL!$U:$U,"PERM") -> 0 | N64: =SUMIFS(MEL!Y:Y,MEL!Y:Y,"<>",MEL!$I:$I,">=0",MEL!$I:$I,"<=9",MEL!$U:$U,"FUT")+SUMIFS(MEL!Y:Y,MEL!Y:Y,"<>",MEL!$I:$I,">=0",MEL!$I:$I,"<=9",MEL!$U:$U,"TEMP") -> 0 | O64: =M64+N64 -> 0
B65: 10 | C65: Drilling systems | D65: =SUMIFS(MEL!R:R,MEL!R:R,"<>",MEL!$I:$I,$B65,MEL!$U:$U,"PERM") -> 0 | E65: =SUMIFS(MEL!R:R,MEL!R:R,"<>",MEL!$I:$I,$B65,MEL!$U:$U,"TEMP")+SUMIFS(MEL!R:R,MEL!R:R,"<>",MEL!$I:$I,$B65,MEL!$U:$U,"FUT") -> 0 | F65: =D65+E65 -> 0 | G65: =SUMIFS(MEL!W:W,MEL!W:W,"<>",MEL!$I:$I,$B65,MEL!$U:$U,"PERM") -> 0 | H65: =SUMIFS(MEL!W:W,MEL!W:W,"<>",MEL!$I:$I,$B65,MEL!$U:$U,"TEMP")+SUMIFS(MEL!W:W,MEL!W:W,"<>",MEL!$I:$I,$B65,MEL!$U:$U,"FUT") -> 0 | I65: =G65+H65 -> 0 | J65: =SUMIFS(MEL!X:X,MEL!X:X,"<>",MEL!$I:$I,$B65,MEL!$U:$U,"PERM") -> 0 | K65: =SUMIFS(MEL!X:X,MEL!X:X,"<>",MEL!$I:$I,$B65,MEL!$U:$U,"TEMP")+SUMIFS(MEL!X:X,MEL!X:X,"<>",MEL!$I:$I,$B65,MEL!$U:$U,"FUT") -> 0 | L65: =J65+K65 -> 0 | M65: =SUMIFS(MEL!Y:Y,MEL!Y:Y,"<>",MEL!$I:$I,$B65,MEL!$U:$U,"PERM") -> 0 | N65: =SUMIFS(MEL!Y:Y,MEL!Y:Y,"<>",MEL!$I:$I,$B65,MEL!$U:$U,"TEMP")+SUMIFS(MEL!Y:Y,MEL!Y:Y,"<>",MEL!$I:$I,$B65,MEL!$U:$U,"FUT") -> 0 | O65: =M65+N65 -> 0
B66: 11 | C66: Drilling process systems | D66: =SUMIFS(MEL!R:R,MEL!R:R,"<>",MEL!$I:$I,B66,MEL!$U:$U,"PERM") -> 0 | E66: =SUMIFS(MEL!R:R,MEL!R:R,"<>",MEL!$I:$I,B66,MEL!$U:$U,"TEMP")+SUMIFS(MEL!R:R,MEL!R:R,"<>",MEL!$I:$I,B66,MEL!$U:$U,"FUT") -> 0 | F66: =D66+E66 -> 0 | G66: =SUMIFS(MEL!W:W,MEL!W:W,"<>",MEL!$I:$I,$B66,MEL!$U:$U,"PERM") -> 0 | H66: =SUMIFS(MEL!W:W,MEL!W:W,"<>",MEL!$I:$I,$B66,MEL!$U:$U,"TEMP")+SUMIFS(MEL!W:W,MEL!W:W,"<>",MEL!$I:$I,$B66,MEL!$U:$U,"FUT") -> 0 | I66: =G66+H66 -> 0 | J66: =SUMIFS(MEL!X:X,MEL!X:X,"<>",MEL!$I:$I,$B66,MEL!$U:$U,"PERM") -> 0 | K66: =SUMIFS(MEL!X:X,MEL!X:X,"<>",MEL!$I:$I,$B66,MEL!$U:$U,"TEMP")+SUMIFS(MEL!X:X,MEL!X:X,"<>",MEL!$I:$I,$B66,MEL!$U:$U,"FUT") -> 0 | L66: =J66+K66 -> 0 | M66: =SUMIFS(MEL!Y:Y,MEL!Y:Y,"<>",MEL!$I:$I,$B66,MEL!$U:$U,"PERM") -> 0 | N66: =SUMIFS(MEL!Y:Y,MEL!Y:Y,"<>",MEL!$I:$I,$B66,MEL!$U:$U,"TEMP")+SUMIFS(MEL!Y:Y,MEL!Y:Y,"<>",MEL!$I:$I,$B66,MEL!$U:$U,"FUT") -> 0 | O66: =M66+N66 -> 0
B67: 12 | C67: Drilling well control systems | D67: =SUMIFS(MEL!R:R,MEL!R:R,"<>",MEL!$I:$I,B67,MEL!$U:$U,"PERM") -> 0 | E67: =SUMIFS(MEL!R:R,MEL!R:R,"<>",MEL!$I:$I,B67,MEL!$U:$U,"TEMP")+SUMIFS(MEL!R:R,MEL!R:R,"<>",MEL!$I:$I,B67,MEL!$U:$U,"FUT") -> 0 | F67: =D67+E67 -> 0 | G67: =SUMIFS(MEL!W:W,MEL!W:W,"<>",MEL!$I:$I,$B67,MEL!$U:$U,"PERM") -> 0 | H67: =SUMIFS(MEL!W:W,MEL!W:W,"<>",MEL!$I:$I,$B67,MEL!$U:$U,"TEMP")+SUMIFS(MEL!W:W,MEL!W:W,"<>",MEL!$I:$I,$B67,MEL!$U:$U,"FUT") -> 0 | I67: =G67+H67 -> 0 | J67: =SUMIFS(MEL!X:X,MEL!X:X,"<>",MEL!$I:$I,$B67,MEL!$U:$U,"PERM") -> 0 | K67: =SUMIFS(MEL!X:X,MEL!X:X,"<>",MEL!$I:$I,$B67,MEL!$U:$U,"TEMP")+SUMIFS(MEL!X:X,MEL!X:X,"<>",MEL!$I:$I,$B67,MEL!$U:$U,"FUT") -> 0 | L67: =J67+K67 -> 0 | M67: =SUMIFS(MEL!Y:Y,MEL!Y:Y,"<>",MEL!$I:$I,$B67,MEL!$U:$U,"PERM") -> 0 | N67: =SUMIFS(MEL!Y:Y,MEL!Y:Y,"<>",MEL!$I:$I,$B67,MEL!$U:$U,"TEMP")+SUMIFS(MEL!Y:Y,MEL!Y:Y,"<>",MEL!$I:$I,$B67,MEL!$U:$U,"FUT") -> 0 | O67: =M67+N67 -> 0
B68: 13 | C68: Riser and well systems topside | D68: =SUMIFS(MEL!R:R,MEL!R:R,"<>",MEL!$I:$I,B68,MEL!$U:$U,"PERM") -> 0 | E68: =SUMIFS(MEL!R:R,MEL!R:R,"<>",MEL!$I:$I,B68,MEL!$U:$U,"TEMP")+SUMIFS(MEL!R:R,MEL!R:R,"<>",MEL!$I:$I,B68,MEL!$U:$U,"FUT") -> 0 | F68: =D68+E68 -> 0 | G68: =SUMIFS(MEL!W:W,MEL!W:W,"<>",MEL!$I:$I,$B68,MEL!$U:$U,"PERM") -> 0 | H68: =SUMIFS(MEL!W:W,MEL!W:W,"<>",MEL!$I:$I,$B68,MEL!$U:$U,"TEMP")+SUMIFS(MEL!W:W,MEL!W:W,"<>",MEL!$I:$I,$B68,MEL!$U:$U,"FUT") -> 0 | I68: =G68+H68 -> 0 | J68: =SUMIFS(MEL!X:X,MEL!X:X,"<>",MEL!$I:$I,$B68,MEL!$U:$U,"PERM") -> 0 | K68: =SUMIFS(MEL!X:X,MEL!X:X,"<>",MEL!$I:$I,$B68,MEL!$U:$U,"TEMP")+SUMIFS(MEL!X:X,MEL!X:X,"<>",MEL!$I:$I,$B68,MEL!$U:$U,"FUT") -> 0 | L68: =J68+K68 -> 0 | M68: =SUMIFS(MEL!Y:Y,MEL!Y:Y,"<>",MEL!$I:$I,$B68,MEL!$U:$U,"PERM") -> 0 | N68: =SUMIFS(MEL!Y:Y,MEL!Y:Y,"<>",MEL!$I:$I,$B68,MEL!$U:$U,"TEMP")+SUMIFS(MEL!Y:Y,MEL!Y:Y,"<>",MEL!$I:$I,$B68,MEL!$U:$U,"FUT") -> 0 | O68: =M68+N68 -> 0
B69: 14 | C69: Drilling control and monitoring systems | D69: =SUMIFS(MEL!R:R,MEL!R:R,"<>",MEL!$I:$I,B69,MEL!$U:$U,"PERM") -> 0 | E69: =SUMIFS(MEL!R:R,MEL!R:R,"<>",MEL!$I:$I,B69,MEL!$U:$U,"TEMP")+SUMIFS(MEL!R:R,MEL!R:R,"<>",MEL!$I:$I,B69,MEL!$U:$U,"FUT") -> 0 | F69: =D69+E69 -> 0 | G69: =SUMIFS(MEL!W:W,MEL!W:W,"<>",MEL!$I:$I,$B69,MEL!$U:$U,"PERM") -> 0 | H69: =SUMIFS(MEL!W:W,MEL!W:W,"<>",MEL!$I:$I,$B69,MEL!$U:$U,"TEMP")+SUMIFS(MEL!W:W,MEL!W:W,"<>",MEL!$I:$I,$B69,MEL!$U:$U,"FUT") -> 0 | I69: =G69+H69 -> 0 | J69: =SUMIFS(MEL!X:X,MEL!X:X,"<>",MEL!$I:$I,$B69,MEL!$U:$U,"PERM") -> 0 | K69: =SUMIFS(MEL!X:X,MEL!X:X,"<>",MEL!$I:$I,$B69,MEL!$U:$U,"TEMP")+SUMIFS(MEL!X:X,MEL!X:X,"<>",MEL!$I:$I,$B69,MEL!$U:$U,"FUT") -> 0 | L69: =J69+K69 -> 0 | M69: =SUMIFS(MEL!Y:Y,MEL!Y:Y,"<>",MEL!$I:$I,$B69,MEL!$U:$U,"PERM") -> 0 | N69: =SUMIFS(MEL!Y:Y,MEL!Y:Y,"<>",MEL!$I:$I,$B69,MEL!$U:$U,"TEMP")+SUMIFS(MEL!Y:Y,MEL!Y:Y,"<>",MEL!$I:$I,$B69,MEL!$U:$U,"FUT") -> 0 | O69: =M69+N69 -> 0
B70: 15 | C70: Drilling drain systems | D70: =SUMIFS(MEL!R:R,MEL!R:R,"<>",MEL!$I:$I,B70,MEL!$U:$U,"PERM") -> 0 | E70: =SUMIFS(MEL!R:R,MEL!R:R,"<>",MEL!$I:$I,B70,MEL!$U:$U,"TEMP")+SUMIFS(MEL!R:R,MEL!R:R,"<>",MEL!$I:$I,B70,MEL!$U:$U,"FUT") -> 0 | F70: =D70+E70 -> 0 | G70: =SUMIFS(MEL!W:W,MEL!W:W,"<>",MEL!$I:$I,$B70,MEL!$U:$U,"PERM") -> 0 | H70: =SUMIFS(MEL!W:W,MEL!W:W,"<>",MEL!$I:$I,$B70,MEL!$U:$U,"TEMP")+SUMIFS(MEL!W:W,MEL!W:W,"<>",MEL!$I:$I,$B70,MEL!$U:$U,"FUT") -> 0 | I70: =G70+H70 -> 0 | J70: =SUMIFS(MEL!X:X,MEL!X:X,"<>",MEL!$I:$I,$B70,MEL!$U:$U,"PERM") -> 0 | K70: =SUMIFS(MEL!X:X,MEL!X:X,"<>",MEL!$I:$I,$B70,MEL!$U:$U,"TEMP")+SUMIFS(MEL!X:X,MEL!X:X,"<>",MEL!$I:$I,$B70,MEL!$U:$U,"FUT") -> 0 | L70: =J70+K70 -> 0 | M70: =SUMIFS(MEL!Y:Y,MEL!Y:Y,"<>",MEL!$I:$I,$B70,MEL!$U:$U,"PERM") -> 0 | N70: =SUMIFS(MEL!Y:Y,MEL!Y:Y,"<>",MEL!$I:$I,$B70,MEL!$U:$U,"TEMP")+SUMIFS(MEL!Y:Y,MEL!Y:Y,"<>",MEL!$I:$I,$B70,MEL!$U:$U,"FUT") -> 0 | O70: =M70+N70 -> 0
B71: 16 | C71: Subsea processing utility systems | D71: =SUMIFS(MEL!R:R,MEL!R:R,"<>",MEL!$I:$I,B71,MEL!$U:$U,"PERM") -> 0 | E71: =SUMIFS(MEL!R:R,MEL!R:R,"<>",MEL!$I:$I,B71,MEL!$U:$U,"TEMP")+SUMIFS(MEL!R:R,MEL!R:R,"<>",MEL!$I:$I,B71,MEL!$U:$U,"FUT") -> 0 | F71: =D71+E71 -> 0 | G71: =SUMIFS(MEL!W:W,MEL!W:W,"<>",MEL!$I:$I,$B71,MEL!$U:$U,"PERM") -> 0 | H71: =SUMIFS(MEL!W:W,MEL!W:W,"<>",MEL!$I:$I,$B71,MEL!$U:$U,"TEMP")+SUMIFS(MEL!W:W,MEL!W:W,"<>",MEL!$I:$I,$B71,MEL!$U:$U,"FUT") -> 0 | I71: =G71+H71 -> 0 | J71: =SUMIFS(MEL!X:X,MEL!X:X,"<>",MEL!$I:$I,$B71,MEL!$U:$U,"PERM") -> 0 | K71: =SUMIFS(MEL!X:X,MEL!X:X,"<>",MEL!$I:$I,$B71,MEL!$U:$U,"TEMP")+SUMIFS(MEL!X:X,MEL!X:X,"<>",MEL!$I:$I,$B71,MEL!$U:$U,"FUT") -> 0 | L71: =J71+K71 -> 0 | M71: =SUMIFS(MEL!Y:Y,MEL!Y:Y,"<>",MEL!$I:$I,$B71,MEL!$U:$U,"PERM") -> 0 | N71: =SUMIFS(MEL!Y:Y,MEL!Y:Y,"<>",MEL!$I:$I,$B71,MEL!$U:$U,"TEMP")+SUMIFS(MEL!Y:Y,MEL!Y:Y,"<>",MEL!$I:$I,$B71,MEL!$U:$U,"FUT") -> 0 | O71: =M71+N71 -> 0
B72: 17 | C72: Subsea processing systems | D72: =SUMIFS(MEL!R:R,MEL!R:R,"<>",MEL!$I:$I,B72,MEL!$U:$U,"PERM") -> 0 | E72: =SUMIFS(MEL!R:R,MEL!R:R,"<>",MEL!$I:$I,B72,MEL!$U:$U,"TEMP")+SUMIFS(MEL!R:R,MEL!R:R,"<>",MEL!$I:$I,B72,MEL!$U:$U,"FUT") -> 0 | F72: =D72+E72 -> 0 | G72: =SUMIFS(MEL!W:W,MEL!W:W,"<>",MEL!$I:$I,$B72,MEL!$U:$U,"PERM") -> 0 | H72: =SUMIFS(MEL!W:W,MEL!W:W,"<>",MEL!$I:$I,$B72,MEL!$U:$U,"TEMP")+SUMIFS(MEL!W:W,MEL!W:W,"<>",MEL!$I:$I,$B72,MEL!$U:$U,"FUT") -> 0 | I72: =G72+H72 -> 0 | J72: =SUMIFS(MEL!X:X,MEL!X:X,"<>",MEL!$I:$I,$B72,MEL!$U:$U,"PERM") -> 0 | K72: =SUMIFS(MEL!X:X,MEL!X:X,"<>",MEL!$I:$I,$B72,MEL!$U:$U,"TEMP")+SUMIFS(MEL!X:X,MEL!X:X,"<>",MEL!$I:$I,$B72,MEL!$U:$U,"FUT") -> 0 | L72: =J72+K72 -> 0 | M72: =SUMIFS(MEL!Y:Y,MEL!Y:Y,"<>",MEL!$I:$I,$B72,MEL!$U:$U,"PERM") -> 0 | N72: =SUMIFS(MEL!Y:Y,MEL!Y:Y,"<>",MEL!$I:$I,$B72,MEL!$U:$U,"TEMP")+SUMIFS(MEL!Y:Y,MEL!Y:Y,"<>",MEL!$I:$I,$B72,MEL!$U:$U,"FUT") -> 0 | O72: =M72+N72 -> 0
B73: 18 | C73: Subsea systems, umbilicals, risers and flowlines (SURF) | D73: =SUMIFS(MEL!R:R,MEL!R:R,"<>",MEL!$I:$I,B73,MEL!$U:$U,"PERM") -> 22.08 | E73: =SUMIFS(MEL!R:R,MEL!R:R,"<>",MEL!$I:$I,B73,MEL!$U:$U,"TEMP")+SUMIFS(MEL!R:R,MEL!R:R,"<>",MEL!$I:$I,B73,MEL!$U:$U,"FUT") -> 4.72 | F73: =D73+E73 -> 26.8 | G73: =SUMIFS(MEL!W:W,MEL!W:W,"<>",MEL!$I:$I,$B73,MEL!$U:$U,"PERM") -> 13400 | H73: =SUMIFS(MEL!W:W,MEL!W:W,"<>",MEL!$I:$I,$B73,MEL!$U:$U,"TEMP")+SUMIFS(MEL!W:W,MEL!W:W,"<>",MEL!$I:$I,$B73,MEL!$U:$U,"FUT") -> 13540 | I73: =G73+H73 -> 26940 | J73: =SUMIFS(MEL!X:X,MEL!X:X,"<>",MEL!$I:$I,$B73,MEL!$U:$U,"PERM") -> 15410 | K73: =SUMIFS(MEL!X:X,MEL!X:X,"<>",MEL!$I:$I,$B73,MEL!$U:$U,"TEMP")+SUMIFS(MEL!X:X,MEL!X:X,"<>",MEL!$I:$I,$B73,MEL!$U:$U,"FUT") -> 15571 | L73: =J73+K73 -> 30981 | M73: =SUMIFS(MEL!Y:Y,MEL!Y:Y,"<>",MEL!$I:$I,$B73,MEL!$U:$U,"PERM") -> 4000 | N73: =SUMIFS(MEL!Y:Y,MEL!Y:Y,"<>",MEL!$I:$I,$B73,MEL!$U:$U,"TEMP")+SUMIFS(MEL!Y:Y,MEL!Y:Y,"<>",MEL!$I:$I,$B73,MEL!$U:$U,"FUT") -> 0 | O73: =M73+N73 -> 4000
B74: 19 | C74: Subsea work-over systems and tooling | D74: =SUMIFS(MEL!R:R,MEL!R:R,"<>",MEL!$I:$I,B74,MEL!$U:$U,"PERM") -> 26.22 | E74: =SUMIFS(MEL!R:R,MEL!R:R,"<>",MEL!$I:$I,B74,MEL!$U:$U,"TEMP")+SUMIFS(MEL!R:R,MEL!R:R,"<>",MEL!$I:$I,B74,MEL!$U:$U,"FUT") -> 0 | F74: =D74+E74 -> 26.22 | G74: =SUMIFS(MEL!W:W,MEL!W:W,"<>",MEL!$I:$I,$B74,MEL!$U:$U,"PERM") -> 24900 | H74: =SUMIFS(MEL!W:W,MEL!W:W,"<>",MEL!$I:$I,$B74,MEL!$U:$U,"TEMP")+SUMIFS(MEL!W:W,MEL!W:W,"<>",MEL!$I:$I,$B74,MEL!$U:$U,"FUT") -> 0 | I74: =G74+H74 -> 24900 | J74: =SUMIFS(MEL!X:X,MEL!X:X,"<>",MEL!$I:$I,$B74,MEL!$U:$U,"PERM") -> 28435 | K74: =SUMIFS(MEL!X:X,MEL!X:X,"<>",MEL!$I:$I,$B74,MEL!$U:$U,"TEMP")+SUMIFS(MEL!X:X,MEL!X:X,"<>",MEL!$I:$I,$B74,MEL!$U:$U,"FUT") -> 0 | L74: =J74+K74 -> 28435 | M74: =SUMIFS(MEL!Y:Y,MEL!Y:Y,"<>",MEL!$I:$I,$B74,MEL!$U:$U,"PERM") -> 0 | N74: =SUMIFS(MEL!Y:Y,MEL!Y:Y,"<>",MEL!$I:$I,$B74,MEL!$U:$U,"TEMP")+SUMIFS(MEL!Y:Y,MEL!Y:Y,"<>",MEL!$I:$I,$B74,MEL!$U:$U,"FUT") -> 0 | O74: =M74+N74 -> 0
B75: 20 | C75: Separation and stabilization systems | D75: =SUMIFS(MEL!R:R,MEL!R:R,"<>",MEL!$I:$I,B75,MEL!$U:$U,"PERM") -> 60.64 | E75: =SUMIFS(MEL!R:R,MEL!R:R,"<>",MEL!$I:$I,B75,MEL!$U:$U,"TEMP")+SUMIFS(MEL!R:R,MEL!R:R,"<>",MEL!$I:$I,B75,MEL!$U:$U,"FUT") -> 2.48 | F75: =D75+E75 -> 63.12 | G75: =SUMIFS(MEL!W:W,MEL!W:W,"<>",MEL!$I:$I,$B75,MEL!$U:$U,"PERM") -> 168600 | H75: =SUMIFS(MEL!W:W,MEL!W:W,"<>",MEL!$I:$I,$B75,MEL!$U:$U,"TEMP")+SUMIFS(MEL!W:W,MEL!W:W,"<>",MEL!$I:$I,$B75,MEL!$U:$U,"FUT") -> 6770 | I75: =G75+H75 -> 175370 | J75: =SUMIFS(MEL!X:X,MEL!X:X,"<>",MEL!$I:$I,$B75,MEL!$U:$U,"PERM") -> 193890 | K75: =SUMIFS(MEL!X:X,MEL!X:X,"<>",MEL!$I:$I,$B75,MEL!$U:$U,"TEMP")+SUMIFS(MEL!X:X,MEL!X:X,"<>",MEL!$I:$I,$B75,MEL!$U:$U,"FUT") -> 7785.5 | L75: =J75+K75 -> 201675.5 | M75: =SUMIFS(MEL!Y:Y,MEL!Y:Y,"<>",MEL!$I:$I,$B75,MEL!$U:$U,"PERM") -> 80000 | N75: =SUMIFS(MEL!Y:Y,MEL!Y:Y,"<>",MEL!$I:$I,$B75,MEL!$U:$U,"TEMP")+SUMIFS(MEL!Y:Y,MEL!Y:Y,"<>",MEL!$I:$I,$B75,MEL!$U:$U,"FUT") -> 0 | O75: =M75+N75 -> 80000
B76: 21 | C76: Crude handling and storage systems. Metering systems | D76: =SUMIFS(MEL!R:R,MEL!R:R,"<>",MEL!$I:$I,B76,MEL!$U:$U,"PERM") -> 0 | E76: =SUMIFS(MEL!R:R,MEL!R:R,"<>",MEL!$I:$I,B76,MEL!$U:$U,"TEMP")+SUMIFS(MEL!R:R,MEL!R:R,"<>",MEL!$I:$I,B76,MEL!$U:$U,"FUT") -> 0 | F76: =D76+E76 -> 0 | G76: =SUMIFS(MEL!W:W,MEL!W:W,"<>",MEL!$I:$I,$B76,MEL!$U:$U,"PERM") -> 0 | H76: =SUMIFS(MEL!W:W,MEL!W:W,"<>",MEL!$I:$I,$B76,MEL!$U:$U,"TEMP")+SUMIFS(MEL!W:W,MEL!W:W,"<>",MEL!$I:$I,$B76,MEL!$U:$U,"FUT") -> 0 | I76: =G76+H76 -> 0 | J76: =SUMIFS(MEL!X:X,MEL!X:X,"<>",MEL!$I:$I,$B76,MEL!$U:$U,"PERM") -> 0 | K76: =SUMIFS(MEL!X:X,MEL!X:X,"<>",MEL!$I:$I,$B76,MEL!$U:$U,"TEMP")+SUMIFS(MEL!X:X,MEL!X:X,"<>",MEL!$I:$I,$B76,MEL!$U:$U,"FUT") -> 0 | L76: =J76+K76 -> 0 | M76: =SUMIFS(MEL!Y:Y,MEL!Y:Y,"<>",MEL!$I:$I,$B76,MEL!$U:$U,"PERM") -> 0 | N76: =SUMIFS(MEL!Y:Y,MEL!Y:Y,"<>",MEL!$I:$I,$B76,MEL!$U:$U,"TEMP")+SUMIFS(MEL!Y:Y,MEL!Y:Y,"<>",MEL!$I:$I,$B76,MEL!$U:$U,"FUT") -> 0 | O76: =M76+N76 -> 0
B77: 23 | C77: Gas compression and re-injection systems | D77: =SUMIFS(MEL!R:R,MEL!R:R,"<>",MEL!$I:$I,B77,MEL!$U:$U,"PERM") -> 0 | E77: =SUMIFS(MEL!R:R,MEL!R:R,"<>",MEL!$I:$I,B77,MEL!$U:$U,"TEMP")+SUMIFS(MEL!R:R,MEL!R:R,"<>",MEL!$I:$I,B77,MEL!$U:$U,"FUT") -> 0 | F77: =D77+E77 -> 0 | G77: =SUMIFS(MEL!W:W,MEL!W:W,"<>",MEL!$I:$I,$B77,MEL!$U:$U,"PERM") -> 0 | H77: =SUMIFS(MEL!W:W,MEL!W:W,"<>",MEL!$I:$I,$B77,MEL!$U:$U,"TEMP")+SUMIFS(MEL!W:W,MEL!W:W,"<>",MEL!$I:$I,$B77,MEL!$U:$U,"FUT") -> 0 | I77: =G77+H77 -> 0 | J77: =SUMIFS(MEL!X:X,MEL!X:X,"<>",MEL!$I:$I,$B77,MEL!$U:$U,"PERM") -> 0 | K77: =SUMIFS(MEL!X:X,MEL!X:X,"<>",MEL!$I:$I,$B77,MEL!$U:$U,"TEMP")+SUMIFS(MEL!X:X,MEL!X:X,"<>",MEL!$I:$I,$B77,MEL!$U:$U,"FUT") -> 0 | L77: =J77+K77 -> 0 | M77: =SUMIFS(MEL!Y:Y,MEL!Y:Y,"<>",MEL!$I:$I,$B77,MEL!$U:$U,"PERM") -> 0 | N77: =SUMIFS(MEL!Y:Y,MEL!Y:Y,"<>",MEL!$I:$I,$B77,MEL!$U:$U,"TEMP")+SUMIFS(MEL!Y:Y,MEL!Y:Y,"<>",MEL!$I:$I,$B77,MEL!$U:$U,"FUT") -> 0 | O77: =M77+N77 -> 0
... B147: 99 | C147: Area completion systems | D147: =SUMIFS(MEL!R:R,MEL!R:R,"<>",MEL!$I:$I,B147,MEL!$U:$U,"PERM") -> 0 | E147: =SUMIFS(MEL!R:R,MEL!R:R,"<>",MEL!$I:$I,B147,MEL!$U:$U,"TEMP")+SUMIFS(MEL!R:R,MEL!R:R,"<>",MEL!$I:$I,B147,MEL!$U:$U,"FUT") -> 0 | F147: =D147+E147 -> 0 | G147: =SUMIFS(MEL!W:W,MEL!W:W,"<>",MEL!$I:$I,$B147,MEL!$U:$U,"PERM") -> 0 | H147: =SUMIFS(MEL!W:W,MEL!W:W,"<>",MEL!$I:$I,$B147,MEL!$U:$U,"TEMP")+SUMIFS(MEL!W:W,MEL!W:W,"<>",MEL!$I:$I,$B147,MEL!$U:$U,"FUT") -> 0 | I147: =G147+H147 -> 0 | J147: =SUMIFS(MEL!X:X,MEL!X:X,"<>",MEL!$I:$I,$B147,MEL!$U:$U,"PERM") -> 0 | K147: =SUMIFS(MEL!X:X,MEL!X:X,"<>",MEL!$I:$I,$B147,MEL!$U:$U,"TEMP")+SUMIFS(MEL!X:X,MEL!X:X,"<>",MEL!$I:$I,$B147,MEL!$U:$U,"FUT") -> 0 | L147: =J147+K147 -> 0 | M147: =SUMIFS(MEL!Y:Y,MEL!Y:Y,"<>",MEL!$I:$I,$B147,MEL!$U:$U,"PERM") -> 0 | N147: =SUMIFS(MEL!Y:Y,MEL!Y:Y,"<>",MEL!$I:$I,$B147,MEL!$U:$U,"TEMP")+SUMIFS(MEL!Y:Y,MEL!Y:Y,"<>",MEL!$I:$I,$B147,MEL!$U:$U,"FUT") -> 0 | O147: =M147+N147 -> 0
B148: Total | D148: =SUM(D64:D147) -> 1107.7519 | E148: =SUM(E64:E147) -> 132.22051 | F148: =SUM(F64:F147) -> 1239.9724 | G148: =SUM(G64:G147) -> 1313778.7 | H148: =SUM(H64:H147) -> 128620 | I148: =SUM(I64:I147) -> 1442398.7 | J148: =SUM(J64:J147) -> 1509317 | K148: =SUM(K64:K147) -> 147913 | ... O148: =SUM(O64:O147) -> 278133.61

Sheet Guidlines
B2: Aibel
B3: EQUIPMENT LIST | N3: Page No.: 2 of 10
N4: Date:24.03.2021
B5: Document No.: C232-AI-R-LA-00001 | N5: Rev. No.: 02
B7: Guidelines for MEL / tag editing
B9: Activity | C9: Description | D9: Format
B10: Establish tag | C10: 1. Insert new row. 2. Set "Tag status" > NEW 3. Fill in tag data. | D10: Row shall be highlighted (Red)
B11: Void tag | C11: 1. Mark row containing tag red, and row to be striked out
B12: Retagging | C12: 1. Rename tag in "MEL" tab. 2. Set "Tag status" > DIFF 3. Store historic tag in separted Excel sheet for tag change tracking | D12: Row shall be highlighted (Red)
B13: Edit tag data | C13: 1. Set "Tag status" > DIFF 2. Change cell content. | D13: Changed/Updated cells shall be highlighted (Orange, Accent
B15: For each new revision, MEL will be stripped of color markings, voided tag removed
B16: and tag status set to blank - Then when further developing the MEL for the next issue,
B17: change marking again to be done.
